Workbook
Name 合併CODE: 對照!$L:$R

Sheet CE店別員別店質List
A3: 計數 - Sold-to
A4: Sold-to | B4: 合併Sold to | C4: 合併Sold Name | D4: 店質 | E4: 業務員 | F4: 業務員部門 | G4: 合計
A5: TW010117A1 | B5: TW010117A1 | C5: 金長益電器 | D5: DC店 | E5: 褚家鳴 | F5: 桃竹營銷處 | G5: 3
A6: TW010157A1 | B6: TW010157A1 | C6: 百鈴電器 | D6: 一般店 | E6: 粘棋欽 | F6: 嘉南營銷處 | G6: 1
A7: TW010274A1 | B7: TW010274A1 | C7: 全省電器 | D7: 專售店 | E7: 歐俊賢 | F7: 嘉南營銷處 | G7: 4
A8: TW010291A1 | B8: TW010291A1 | C8: 聯鈦冷凍空調電器行 | D8: DC店 | E8: 黃坤鎮 | F8: 嘉南營銷處 | G8: 2
A9: TW010303A1 | B9: TW010303A1 | C9: 明聳企業 | D9: 一般店 | E9: 吳章瑋 | F9: AC Team | G9: 1
A10: TW010429A1 | B10: TW010429A1 | C10: 金亞實業 | D10: 專售店 | E10: 錢亮均 | F10: 台北營銷處 | G10: 4
A11: TW010431A1 | B11: TW010431A1 | C11: 萬豐視聽 | D11: DC店 | E11: 錢亮均 | F11: 台北營銷處 | G11: 2
A12: TW010435A1 | B12: TW010435A1 | C12: 上順電器 | D12: 一般店 | E12: 錢亮均 | F12: 台北營銷處 | G12: 2
A13: TW010437A1 | B13: TW010437A1 | C13: 今漢 | D13: 專售店 | E13: 錢亮均 | F13: 台北營銷處 | G13: 4
A14: TW010455A1 | B14: TW010455A1 | C14: 昇廣電器 | D14: 一般店 | E14: 陳慶全 | F14: 台中營銷處 | G14: 1
A15: TW010457A1 | B15: TW010457A1 | C15: 錦穗實業 | D15: 一般店 | E15: 歐俊賢 | F15: 嘉南營銷處 | G15: 1
A16: TW010458A1 | B16: TW010458A1 | C16: 大時代量販 | D16: DC店 | E16: 江柏慶 | F16: 嘉南營銷處 | G16: 1
... A704: TW019319A1 | B704: TW019319A1 | C704: 泰安電器生活館 | D704: 一般店 | E704: 褚家鳴 | F704: 桃竹營銷處 | G704: 3
A705: TW019320A1 | B705: TW019320A1 | C705: 思納捷科技 | E705: 陳崴 | F705: AC Team | G705: 1
A706: 總計 | G706: 1499

Sheet Ship to
A1: 業務員 | B1: 業務員部門 | C1: 店質 | D1: 特殊 | E1: 合併Sold to | F1: 合併Sold Name | G1: Sales Department | H1: Sales Channel Name | I1: Pricing Group Name | J1: Business Area | K1: Legal Entity Code | L1: Legal Entity Name | M1: Sold-to | N1: Sold-to Name | O1: Ship To Code | P1: Ship To Name (Local) | Q1: Ship-to Type | R1: Default (Sales Only) | S1: Store No | T1: Inactive Flag | U1: Ship Group | V1: Ship Group Name | W1: Ship Group Default | X1: Carrier | Y1: TAX Ship-to Code | Z1: Business Registration No | AA1: Region | AB1: Region Description | AC1: Province | AD1: County | AE1: Postal Code | AF1: City | AG1: Street 1 | AH1: Street 2 | AI1: Street 3 | AJ1: Street 4 | AK1: Country | AL1: Contact Person Name | AM1: Contact Person's Mobile | AN1: Usage | AO1: Environmental Fee Flag | AP1: Same Address Code | AQ1: Created On | AR1: Created By | AS1: Changed On | AT1: Changed By | AU1: Company | AV1: Sales Organization | AW1: Distr. Channel | AX1: Created On
A2: 林建宏 | B2: MMCS | C2: 萬家福 | E2: TW012801A1 | F2: 康達盛通生活事業 | G2: MM Part | H2: 萬家福 | I2: 萬家福 | J2: SAL | K2: TW01280100 | L2: 家福股份有限公司總公司-IT | M2: TW012801A1 | N2: 康達盛通生活事業 | O2: TWSG000718 | P2: 三民家福 | Q2: S | S2: MM000101 | X2: TW012676 | Z2: 2794080* | AE2: 105 | AG2: 台北市松山區三民路160號 | AK2: TW | AL2: 陳政道 | AN2: D | AO2: X | AQ2: 2025.11.25 14:58:30 | AR2: 정한석 hanseok.jung@lgepartner.com | AS2: 2026.08.06 10:15:22 | AT2: 노용훈 yonghoon1.noh@lgepartner.com | AU2: EATT | AV2: [LGETT] Common | AW2: Domestic | AX2: 45986
A3: 陳志豐 | B3: 高屏營銷處 | C3: DC店 | E3: TW219300A1 | F3: 弘昇電器行 | G3: AC Team | H3: AC TEAM | I3: DC店 | J3: SAL | K3: TW21930000 | L3: 弘昇電器行 | M3: TW219300A1 | N3: 弘昇電器行 | O3: TWSG001536 | P3: 弘昇電器行(倉庫) | Q3: S | S3: DL003829-S | X3: TW012676 | Z3: 8102123* | AE3: 832 | AG3: 高雄市林園區溪州里溪州二路115巷92號 | AK3: TW | AL3: 謝文弘 | AN3: D | AO3: X | AQ3: 2025.11.25 14:58:35 | AR3: 정한석 hanseok.jung@lgepartner.com | AS3: 2026.07.27 13:15:16 | AT3: PinFang Wang sarah.wang@lge.com | AU3: EATT | AV3: [LGETT] Common | AW3: Domestic | AX3: 45986
A4: #N/A | B4: #N/A | E4: TW219128A1 | F4: ONE TIME SERVICE FOR TYPE 3 | G4: Tech Support Part | H4: SVC | J4: SAL | K4: TW21912800 | L4: ONE TIME SERVICE FOR TYPE 3 | M4: TW219128A1 | N4: ONE TIME SERVICE FOR TYPE 3 | O4: TWSG003597 | P4: One time_SVC AC | Q4: B | X4: TW012676 | AE4: 114 | AG4: 台北市內湖區基湖路3巷47號6樓 | AK4: TW | AL4: * | AN4: M | AO4: X | AQ4: 2026.04.21 16:42:32 | AR4: 김승윤 seungyun2.kim@lgepartner.com | AS4: 2026.06.26 21:32:43 | AT4: 노용훈 yonghoon1.noh@lgepartner.com | AU4: EATT | AV4: [LGETT] Common | AW4: Domestic | AX4: 46133
A5: 沈勇良 | B5: 高屏營銷處 | C5: 一般店 | E5: TW219645A1 | F5: 源洲工程有限公司 | G5: Dealer Sales_KaoPing Team | H5: 高屏營銷處 | I5: 一般店 | J5: SAL | K5: TW21964500 | L5: 源洲工程有限公司 | M5: TW219645A1 | N5: 源洲工程有限公司 | O5: TWSG002905 | P5: 源洲工程有限公司 | Q5: S | R5: Y | S5: TW007855-S | X5: TW012676 | Z5: 4279184* | AE5: 814 | AG5: 高雄市仁武區埤內巷17號 | AK5: TW | AL5: 邱淵豐 | AN5: M | AO5: X | AQ5: 2025.11.25 14:58:36 | AR5: 정한석 hanseok.jung@lgepartner.com | AS5: 2026.06.26 20:03:29 | AT5: 노용훈 yonghoon1.noh@lgepartner.com | AU5: EATT | AV5: [LGETT] Common | AW5: Domestic | AX5: 45986
A6: 陳俊宏 | B6: 百貨 | C6: 百貨 | E6: TW014445A1 | F6: 集雅社 | G6: Department Store Team | H6: 百貨 | I6: 百貨 | J6: SAL | K6: TW01444500 | L6: 集雅社股份有限公司 | M6: TW014445A1 | N6: 集雅社 | O6: TWSG001258 | P6: 集雅社-新北-汐止遠雄 | Q6: S | S6: DL003621-S | X6: TW012676 | Z6: 8926617* | AE6: 221 | AG6: 新北市汐止區新台五路一段93-99號1樓 | AK6: TW | AL6: * | AN6: D | AO6: X | AQ6: 2025.11.25 14:58:36 | AR6: 정한석 hanseok.jung@lgepartner.com | AS6: 2026.06.26 20:03:39 | AT6: 노용훈 yonghoon1.noh@lgepartner.com | AU6: EATT | AV6: [LGETT] Common | AW6: Domestic | AX6: 45986
A7: 黃宗平 | B7: IT Part | C7: IT | E7: TW219603A1 | F7: 集雅社 | G7: LGETT | H7: IT | I7: IT | J7: SAL | K7: TW01444500 | L7: 集雅社股份有限公司 | M7: TW219603A1 | N7: 集雅社 | O7: TWSG003259 | P7: 集雅社-宜蘭-新月廣場 | Q7: S | S7: IT001234-S | X7: TW012676 | Z7: 8926617* | AE7: 260 | AG7: 宜蘭縣宜蘭市民權路二段38巷6號3樓 | AK7: TW | AL7: * 李念慈 | AN7: D | AO7: X | AQ7: 2025.11.25 14:58:40 | AR7: 정한석 hanseok.jung@lgepartner.com | AS7: 2026.06.26 20:21:34 | AT7: 노용훈 yonghoon1.noh@lgepartner.com | AU7: EATT | AV7: [LGETT] Common | AW7: Domestic | AX7: 45986
A8: 陳崴 | B8: AC Team | C8: 一般店 | E8: TW019123A1 | F8: 沅新空調 | G8: LGETT | H8: AC TEAM | I8: 一般店 | J8: SAL | K8: TW01912300 | L8: 沅新空調 | M8: TW019123A1 | N8: 沅新空調 | O8: TWSG003185 | P8: 沅新空調 | Q8: S | R8: Y | S8: TW007869-S | X8: TW012676 | Z8: 2497963* | AE8: 831 | AG8: 高雄市大寮區打鐵店街26巷173-3號 | AK8: TW | AL8: 郭力榮 | AM8: 0935853661 | AN8: M | AO8: X | AQ8: 2025.11.25 14:58:23 | AR8: 정한석 hanseok.jung@lgepartner.com | AS8: 2026.06.26 20:27:37 | AT8: 노용훈 yonghoon1.noh@lgepartner.com | AU8: EATT | AV8: [LGETT] Common | AW8: Domestic | AX8: 45986
A9: 陳昱宏 | B9: MMCS | C9: 大同 | E9: TW018199A1 | F9: 大同綜合訊電(股) | G9: CS Part | H9: 大同 | I9: 大同 | J9: SAL | K9: TW01819900 | L9: 大同綜合訊電股份有限公司 | M9: TW018199A1 | N9: 大同綜合訊電(股) | O9: TWSG002209 | P9: 1130汐止大同大同 | Q9: S | S9: 1130T | X9: TW012676 | Z9: 7078852* | AE9: 221 | AG9: 台北縣汐止市大同路二段497號 | AK9: TW | AL9: * | AN9: D | AO9: X | AQ9: 2025.11.25 14:58:42 | AR9: 정한석 hanseok.jung@lgepartner.com | AS9: 2026.06.26 20:32:59 | AT9: 노용훈 yonghoon1.noh@lgepartner.com | AU9: EATT | AV9: [LGETT] Common | AW9: Domestic | AX9: 45986
A10: 郭本威 | B10: OBS | C10: OBS | E10: TW015380A1 | F10: 康迅數位整合股份有限公司 | G10: OBS Team | H10: OBS | I10: OBS | J10: SAL | K10: TW01538000 | L10: 康迅數位整合股份有限公司 | M10: TW015380A1 | N10: 康迅數位整合股份有限公司 | O10: TWSG003129 | P10: ONE TIME OBS(D2B2C_PAYEASY OMV) | Q10: S | S10: DL004338-S | X10: TW012676 | Z10: 7055321* | AG10: * | AK10: TW | AL10: * | AN10: M | AO10: X | AQ10: 2025.11.25 14:58:38 | AR10: 정한석 hanseok.jung@lgepartner.com | AS10: 2026.06.26 21:00:04 | AT10: 노용훈 yonghoon1.noh@lgepartner.com | AU10: EATT | AV10: [LGETT] Common | AW10: Domestic | AX10: 45986
A11: 蔣承孝 | B11: 高屏營銷處 | C11: 專售店 | E11: TW219187A1 | F11: 棋杰電器行 | G11: Dealer Sales_KaoPing Team | H11: 高屏營銷處 | I11: 專售店 | J11: SAL | K11: TW21918700 | L11: 棋杰電器 | M11: TW219187A1 | N11: 棋杰電器 | O11: TWSG000317 | P11: 棋杰電器行(東源倉) | Q11: S | S11: DL004009-S | X11: TW012676 | Z11: 0801687* | AE11: 821 | AG11: 高雄市路竹區民族路132號 | AK11: TW | AL11: 棋杰電器行(東源倉) | AN11: D | AO11: X | AQ11: 2025.11.25 14:58:23 | AR11: 정한석 hanseok.jung@lgepartner.com | AS11: 2026.06.26 21:00:58 | AT11: 노용훈 yonghoon1.noh@lgepartner.com | AU11: EATT | AV11: [LGETT] Common | AW11: Domestic | AX11: 45986
A12: #N/A | B12: #N/A | C12: B2B2C | E12: TW019190A1 | F12: 匯聚科技 | G12: B2B2C Sales Part | H12: B2B2C(B2B2C Part) | I12: B2B2C | J12: SAL | K12: TW01919000 | L12: 匯聚科技 | M12: TW019190A1 | N12: 匯聚科技 | O12: TWSG003436 | P12: 匯聚科技 | Q12: S | R12: Y | S12: TW007901-S | X12: TW012676 | Z12: 2786858* | AE12: 241 | AG12: 新北市三重區重新路5段646之1號 | AK12: TW | AL12: 吳宛蓁 | AM12: 0970-779796 | AN12: M | AO12: X | AQ12: 2025.11.25 14:58:29 | AR12: 정한석 hanseok.jung@lgepartner.com | AS12: 2026.06.26 21:06:49 | AT12: 노용훈 yonghoon1.noh@lgepartner.com | AU12: EATT | AV12: [LGETT] Common | AW12: Domestic | AX12: 45986
A13: 施漢鵬 | B13: MMCS | C13: 富山淨水 | E13: TW019125A1 | F13: 富山淨水 | G13: MM Part | H13: 富山淨水 | I13: 富山淨水 | J13: SAL | K13: TW01912500 | L13: 富山淨水 | M13: TW019125A1 | N13: 富山淨水 | O13: TWSG003186 | P13: 富山淨水 | Q13: S | R13: Y | S13: TW007871-S | X13: TW012676 | Z13: 2770281* | AE13: 813 | AG13: 高雄市左營區新上里明誠二路515號1樓 | AK13: TW | AL13: 劉崇睿 | AM13: 0931-921-751 | AN13: M | AO13: X | AQ13: 2025.11.25 14:58:26 | AR13: 정한석 hanseok.jung@lgepartner.com | AS13: 2026.06.26 21:06:49 | AT13: 노용훈 yonghoon1.noh@lgepartner.com | AU13: EATT | AV13: [LGETT] Common | AW13: Domestic | AX13: 45986
A14: #N/A | B14: #N/A | E14: TW219139A1 | F14: ONE TIME CUSTOMER | G14: LGETT | H14: ETC | J14: SAL | K14: TW21913900 | L14: ONE TIME CUSTOMER | M14: TW219139A1 | N14: ONE TIME CUSTOMER | O14: TWSG000147 | P14: ONE TIME CUSTOMER | Q14: S | R14: Y | S14: TW006241 | X14: TW012676 | Z14: * | AE14: 114 | AG14: 台北市內湖區基湖路3巷47號7樓 | AK14: TW | AL14: 0 | AN14: D | AO14: X | AQ14: 2025.11.25 14:58:36 | AR14: 정한석 hanseok.jung@lgepartner.com | AS14: 2026.06.26 21:09:56 | AT14: 노용훈 yonghoon1.noh@lgepartner.com | AU14: EATT | AV14: [LGETT] Common | AW14: Domestic | AX14: 45986
A15: 葉作仁 | B15: 桃竹營銷處 | C15: 一般店 | E15: TW219384A1 | F15: 天籟企業社 | G15: Dealer Sales_TaoChu Team | H15: 桃竹營銷處 | I15: 一般店 | J15: SAL | K15: TW21938400 | L15: 天籟企業社 | M15: TW219384A1 | N15: 天籟企業社 | O15: TWSG000747 | P15: 天籟企業社 | Q15: S | S15: TW007296 | X15: TW012676 | Z15: 4996773* | AE15: 320 | AG15: 桃園市楊梅區大華街27號 | AK15: TW | AL15: * 李秀民 | AN15: D | AO15: X | AQ15: 2025.11.25 14:58:36 | AR15: 정한석 hanseok.jung@lgepartner.com | AS15: 2026.06.26 21:15:02 | AT15: 노용훈 yonghoon1.noh@lgepartner.com | AU15: EATT | AV15: [LGETT] Common | AW15: Domestic | AX15: 45986
A16: 吳睿涵 | B16: E-Commerce | C16: ONLINE | E16: TW219605A1 | F16: 富基電通 | G16: E-Commerce Team | H16: ONLINE | I16: ONLINE | J16: SAL | K16: TW01370200 | L16: 富基電通股份有限公司 | M16: TW219605A1 | N16: 富基電通 | O16: TWSG000692 | P16: 富基電通(大園倉庫) | Q16: S | S16: DL003971-S | X16: TW012676 | Z16: 2752554* | AE16: 337 | AG16: 桃園市大園區開和路2號 | AK16: TW | AL16: 莊詩弘 | AN16: D | AO16: X | AQ16: 2025.11.25 14:58:37 | AR16: 정한석 hanseok.jung@lgepartner.com | AS16: 2026.06.26 21:58:50 | AT16: 노용훈 yonghoon1.noh@lgepartner.com | AU16: EATT | AV16: [LGETT] Common | AW16: Domestic | AX16: 45986
A17: 葉日崧 | B17: MMCS | C17: 全國 | E17: TW014442A1 | F17: 全國電子 | G17: CS Part | H17: 全國 | I17: 全國 | J17: SAL | K17: TW01444200 | L17: 全國電子股份有限公司 | M17: TW014442A1 | N17: 全國電子 | O17: TWSG003406 | P17: 3083全國電子(湳雅) | Q17: S | S17: CS001619-S | X17: TW012676 | Z17: 2200625* | AE17: 300 | AG17: 新竹市湳雅街89號1樓 | AK17: TW | AL17: * | AN17: D | AO17: X | AQ17: 2025.11.25 14:58:36 | AR17: 정한석 hanseok.jung@lgepartner.com | AS17: 2026.06.26 19:49:51 | AT17: 노용훈 yonghoon1.noh@lgepartner.com | AU17: EATT | AV17: [LGETT] Common | AW17: Domestic | AX17: 45986
A18: 林宜慧 | B18: E-Commerce | C18: ONLINE | E18: TW219378A1 | F18: 爆器顧問股份有限公司 | G18: E-Commerce Team | H18: ONLINE | I18: ONLINE | J18: SAL | K18: TW21937800 | L18: 爆器顧問股份有限公司 | M18: TW219378A1 | N18: 爆器顧問股份有限公司 | O18: TWSG000208 | P18: 爆器顧問股份有限公司 | Q18: S | R18: Y | S18: TW007290-S | X18: TW012676 | Z18: 8507710* | AE18: 236 | AG18: 新北市土城區裕生路８６巷１２號３樓 | AK18: TW | AL18: 林書弘 | AM18: 0933088894 | AN18: D | AO18: X | AQ18: 2025.11.25 14:58:34 | AR18: 정한석 hanseok.jung@lgepartner.com | AS18: 2026.06.26 19:49:58 | AT18: 노용훈 yonghoon1.noh@lgepartner.com | AU18: EATT | AV18: [LGETT] Common | AW18: Domestic | AX18: 45986
A19: 黃坤鎮 | B19: 嘉南營銷處 | C19: DC店 | E19: TW018827A1 | F19: 中美電器行 | G19: Dealer Sales_ChiaNan Team | H19: 嘉南營銷處 | I19: DC店 | J19: SAL | K19: TW01882700 | L19: 中美電器行 | M19: TW018827A1 | N19: 中美電器行 | O19: TWSG002168 | P19: 中美電器行(莿桐倉) | Q19: S | S19: DL004221-S | X19: TW012676 | Z19: 9282483* | AE19: 647 | AG19: 雲林縣莿桐鄉埔尾村油車路31-1號 | AK19: TW | AL19: * | AN19: D | AO19: X | AQ19: 2025.11.25 14:58:42 | AR19: 정한석 hanseok.jung@lgepartner.com | AS19: 2026.06.26 19:50:03 | AT19: 노용훈 yonghoon1.noh@lgepartner.com | AU19: EATT | AV19: [LGETT] Common | AW19: Domestic | AX19: 45986
A20: 林宜慧 | B20: E-Commerce | C20: ONLINE | E20: TW016899A1 | F20: 包昇股份有限公司 | G20: E-Commerce Team | H20: ONLINE | I20: ONLINE | J20: SAL | K20: TW01689900 | L20: 包昇數位文化有限公司 | M20: TW016899A1 | N20: 包昇股份有限公司 | O20: TWSG000895 | P20: 包昇數位(特捷倉) | Q20: S | S20: DL003669-S | X20: TW012676 | Z20: 5312315* | AE20: 224 | AG20: 新北市瑞芳區楓仔瀨路1巷1號A1棟 | AK20: TW | AL20: 渠淑惠 | AN20: D | AO20: X | AQ20: 2025.11.25 14:58:43 | AR20: 정한석 hanseok.jung@lgepartner.com | AS20: 2026.06.26 19:50:14 | AT20: 노용훈 yonghoon1.noh@lgepartner.com | AU20: EATT | AV20: [LGETT] Common | AW20: Domestic | AX20: 45986
A21: 連承剛 | B21: 百貨 | C21: 百貨 | E21: TW011485A1 | F21: 秀翔 | G21: Department Store Team | H21: 百貨 | I21: 百貨 | J21: SAL | K21: TW01148500 | L21: 秀翔實業有限公司 | M21: TW011485A1 | N21: 秀翔 | O21: TWSG001052 | P21: 秀翔-高雄-新光三越-三多 | Q21: S | S21: DL004442 | X21: TW012676 | Z21: 8942969* | AE21: 806 | AG21: 高雄市前鎮區三多三路213號10樓 | AK21: TW | AL21: 潘玉慧 歐怡玲 | AM21: 09108006080921976013 | AN21: D | AO21: X | AQ21: 2025.11.25 14:58:43 | AR21: 정한석 hanseok.jung@lgepartner.com | AS21: 2026.06.26 19:50:18 | AT21: 노용훈 yonghoon1.noh@lgepartner.com | AU21: EATT | AV21: [LGETT] Common | AW21: Domestic | AX21: 45986
A22: 陳志豐 | B22: 高屏營銷處 | C22: 一般店 | E22: TW219379A1 | F22: 雲彩企業社 | G22: Dealer Sales_KaoPing Team | H22: 高屏營銷處 | I22: 一般店 | J22: SAL | K22: TW21937900 | L22: 雲彩企業社 | M22: TW219379A1 | N22: 雲彩企業社 | O22: TWSG000746 | P22: 雲彩企業社 | Q22: S | R22: Y | S22: TW007291-S | X22: TW012676 | Z22: 8876381* | AE22: 920 | AG22: 屏東縣潮州鎮三共里朝昇路４１號１樓 | AK22: TW | AL22: 賴財正 | AM22: 0921-581-550 | AN22: D | AO22: X | AQ22: 2025.11.25 14:58:36 | AR22: 정한석 hanseok.jung@lgepartner.com | AS22: 2026.06.26 20:01:52 | AT22: 노용훈 yonghoon1.noh@lgepartner.com | AU22: EATT | AV22: [LGETT] Common | AW22: Domestic | AX22: 45986
A23: 陳俊芳 | B23: MMCS | C23: 燦坤 | E23: TW014426A1 | F23: 燦坤 | G23: CS Part | H23: 燦坤 | I23: 燦坤 | J23: SAL | K23: TW01442600 | L23: 燦坤實業股份有限公司 | M23: TW014426A1 | N23: 燦坤 | O23: TWSG001699 | P23: 626嘉義新港燦坤 | Q23: S | S23: 626 | X23: TW012676 | Z23: 6956800* | AE23: 616 | AG23: 嘉義縣新港鄉中山路72巷2-3號 | AK23: TW | AL23: * | AN23: D | AO23: X | AQ23: 2025.11.25 14:58:32 | AR23: 정한석 hanseok.jung@lgepartner.com | AS23: 2026.06.26 20:03:53 | AT23: 노용훈 yonghoon1.noh@lgepartner.com | AU23: EATT | AV23: [LGETT] Common | AW23: Domestic | AX23: 45986
A24: 陳勇志 | B24: MMCS | C24: 全聯 | E24: TW014431A1 | F24: 大潤發總公司 | G24: MM Dept. | H24: 大潤發 | I24: 全聯 | J24: SAL | K24: TW01443100 | L24: 大潤發流通事業股份有限公司 | M24: TW014431A1 | N24: 大潤發總公司 | O24: TWSG002791 | P24: 75大潤發供應鍊(外箱) | Q24: S | S24: MM000229-S | X24: TW012676 | Z24: 9716556* | AE24: 328 | AG24: 桃園市觀音鄉上大村大湖路一段298號(外箱) | AK24: TW | AL24: 大潤發觀音倉(外箱) | AN24: D | AO24: X | AQ24: 2025.11.25 14:58:36 | AR24: 정한석 hanseok.jung@lgepartner.com | AS24: 2026.06.26 20:09:11 | AT24: 노용훈 yonghoon1.noh@lgepartner.com | AU24: EATT | AV24: [LGETT] Common | AW24: Domestic | AX24: 45986
A25: 林威豪 | B25: 桃竹營銷處 | C25: 專售店 | E25: TW219348A1 | F25: 克拉企業 | G25: Dealer Sales_TaoChu Team | H25: 桃竹營銷處 | I25: 專售店 | J25: SAL | K25: TW21934800 | L25: 克拉企業 | M25: TW219348A1 | N25: 克拉企業 | O25: TWSG001354 | P25: 克拉企業(忠義倉) | Q25: S | S25: DL004120-S | X25: TW012676 | Z25: 6967086* | AE25: 333 | AG25: 桃園市龜山區忠義路一段1043巷42弄109號 | AK25: TW | AL25: * | AN25: D | AO25: X | AQ25: 2025.11.25 14:58:30 | AR25: 정한석 hanseok.jung@lgepartner.com | AS25: 2026.06.26 20:09:27 | AT25: 노용훈 yonghoon1.noh@lgepartner.com | AU25: EATT | AV25: [LGETT] Common | AW25: Domestic | AX25: 45986
A26: 江柏慶 | B26: 嘉南營銷處 | C26: DC店 | E26: TW010966A1 | F26: 信福電器 | G26: Dealer Sales_ChiaNan Team | H26: 嘉南營銷處 | I26: DC店 | J26: SAL | K26: TW01096600 | L26: 信福電器有限公司 | M26: TW010966A1 | N26: 信福電器 | O26: TWSG001919 | P26: 信福電器(路竹民族) | Q26: S | S26: DL004018-S | X26: TW012676 | Z26: 6927921* | AE26: 821 | AG26: 高雄市路竹區民族路132號 | AK26: TW | AL26: * | AN26: D | AO26: X | AQ26: 2025.11.25 14:58:41 | AR26: 정한석 hanseok.jung@lgepartner.com | AS26: 2026.06.26 20:09:54 | AT26: 노용훈 yonghoon1.noh@lgepartner.com | AU26: EATT | AV26: [LGETT] Common | AW26: Domestic | AX26: 45986
A27: 陳勇志 | B27: MMCS | C27: 全聯 | E27: TW018211A1 | F27: 大潤發嘉義 | G27: MM Part | H27: 大潤發 | I27: 全聯 | J27: SAL | K27: TW01821100 | L27: 大潤發流通事業股份有限公司嘉義分公司 | M27: TW018211A1 | N27: 大潤發嘉義 | O27: TWSG001648 | P27: 36大潤發嘉義 | Q27: S | S27: MM000130 | X27: TW012676 | Z27: 2843616* | AE27: 600 | AG27: 嘉義市博愛路2段281號 | AK27: TW | AL27: 大潤發流通事業股份有限公司 | AN27: D | AO27: X | AQ27: 2025.11.25 14:58:32 | AR27: 정한석 hanseok.jung@lgepartner.com | AS27: 2026.06.26 20:09:54 | AT27: 노용훈 yonghoon1.noh@lgepartner.com | AU27: EATT | AV27: [LGETT] Common | AW27: Domestic | AX27: 45986
A28: #N/A | B28: #N/A | C28: DC店 | E28: TW018373A1 | F28: 新秀國際企業有限公司 | G28: Dealer Sales_Taipei Team | H28: 台北營銷處 | I28: DC店 | J28: SAL | K28: TW01837300 | L28: 新秀國際企業 | M28: TW018373A1 | N28: 新秀國際企業有限公司 | O28: TWSG003053 | P28: 新秀國際-中壢元化店 | Q28: S | S28: DL003636 | X28: TW012676 | Z28: 5096891* | AE28: 320 | AG28: 桃園縣中壢市元化路2段30號1樓 | AK28: TW | AL28: 王鵬凱 | AN28: D | AO28: X | AQ28: 2025.11.25 14:58:28 | AR28: 정한석 hanseok.jung@lgepartner.com | AS28: 2026.06.26 20:10:05 | AT28: 노용훈 yonghoon1.noh@lgepartner.com | AU28: EATT | AV28: [LGETT] Common | AW28: Domestic | AX28: 45986
A29: 蔣承孝 | B29: 高屏營銷處 | C29: 專售店 | E29: TW219617A1 | F29: 九三電器有限公司 | G29: Dealer Sales_KaoPing Team | H29: 高屏營銷處 | I29: 專售店 | J29: SAL | K29: TW21945500 | L29: 九三電器有限公司 | M29: TW219617A1 | N29: 九三電器有限公司 | O29: TWSG002931 | P29: 九三電器(路竹倉) | Q29: S | S29: DL004124-S | X29: TW012676 | Z29: 2466809* | AE29: 821 | AG29: 高雄市路竹區民族路132號 | AK29: TW | AL29: 蘇泳瑄 | AM29: 0956168517 | AN29: D | AO29: X | AQ29: 2025.11.25 14:58:34 | AR29: 정한석 hanseok.jung@lgepartner.com | AS29: 2026.06.26 20:21:27 | AT29: 노용훈 yonghoon1.noh@lgepartner.com | AU29: EATT | AV29: [LGETT] Common | AW29: Domestic | AX29: 45986
A30: 陳志豐 | B30: 高屏營銷處 | C30: 專售店 | E30: TW013493A1 | F30: 晉宏電器 | G30: Dealer Sales_KaoPing Team | H30: 高屏營銷處 | I30: 專售店 | J30: SAL | K30: TW01349300 | L30: 晉宏電器行 | M30: TW013493A1 | N30: 晉宏電器 | O30: TWSG001177 | P30: 晉宏電器(送貨地址) | Q30: S | S30: DL002745 | X30: TW012676 | Z30: 9096489* | AE30: 928 | AG30: 屏東縣東港鎮中正路228號 | AK30: TW | AL30: 晉宏電器行(送貨地址) | AN30: D | AO30: X | AQ30: 2025.11.25 14:58:32 | AR30: 정한석 hanseok.jung@lgepartner.com | AS30: 2026.06.26 20:26:02 | AT30: 노용훈 yonghoon1.noh@lgepartner.com | AU30: EATT | AV30: [LGETT] Common | AW30: Domestic | AX30: 45986
A31: 葉作仁 | B31: 桃竹營銷處 | C31: 一般店 | E31: TW012596A1 | F31: 桃竹苗電器 | G31: Dealer Sales_TaoChu Team | H31: 桃竹營銷處 | I31: 一般店 | J31: SAL | K31: TW01259600 | L31: 桃竹苗電器有限公司 | M31: TW012596A1 | N31: 桃竹苗電器 | O31: TWSG003515 | P31: 桃竹苗電器(平鎮水廠路) | Q31: S | S31: DL004478-S | X31: TW012676 | Z31: 8952776* | AE31: 324 | AG31: 桃園市平鎮區水廠路12號 | AK31: TW | AL31: * 李文旭 | AN31: M | AO31: X | AQ31: 2026.02.06 08:00:06 | AR31: B_SS_ZZZZ001 | AS31: 2026.06.26 21:32:27 | AT31: 노용훈 yonghoon1.noh@lgepartner.com | AU31: EATT | AV31: [LGETT] Common | AW31: Domestic | AX31: 46059
A32: 連承剛 | B32: 百貨 | C32: 百貨 | E32: TW219296A1 | F32: 丹意企業 | G32: Department Store Team | H32: 百貨 | I32: 百貨 | J32: SAL | K32: TW21929600 | L32: 丹意企業 | M32: TW219296A1 | N32: 丹意企業 | O32: TWSG003640 | P32: 丹意(B&O)-板橋大遠百門市 | Q32: S | S32: DL003709-S | X32: TW012676 | Z32: 2846540* | AE32: 220 | AG32: 新北市板橋區新站路28號2樓 | AK32: TW | AL32: * 楊昆松 | AN32: M | AO32: X | AQ32: 2026.05.16 08:00:04 | AR32: B_SS_ZZZZ001 | AS32: 2026.06.26 21:32:41 | AT32: 노용훈 yonghoon1.noh@lgepartner.com | AU32: EATT | AV32: [LGETT] Common | AW32: Domestic | AX32: 46158
A33: 錢亮均 | B33: 台北營銷處 | C33: 一般店 | E33: TW011559A1 | F33: 宏億電器行 | G33: LGETT | H33: 台北營銷處 | I33: 一般店 | J33: SAL | K33: TW01155900 | L33: 宏億電器行 | M33: TW011559A1 | N33: 宏億電器行 | O33: TWSG003576 | P33: 宏億電器行 | Q33: S | S33: TW003045-S | X33: TW012676 | Z33: 9586982* | AE33: 221 | AG33: 新北市汐止區建成路３７巷９號 | AK33: TW | AL33: 廖儒慶 | AM33: 0955500280 | AN33: M | AO33: X | AQ33: 2026.04.14 08:00:04 | AR33: B_SS_ZZZZ001 | AS33: 2026.06.26 21:32:44 | AT33: 노용훈 yonghoon1.noh@lgepartner.com | AU33: EATT | AV33: [LGETT] Common | AW33: Domestic | AX33: 46126
A34: 褚家鳴 | B34: 桃竹營銷處 | C34: DC店 | E34: TW010884A1 | F34: 金一電器 | G34: Dealer Sales_TaoChu Team | H34: 桃竹營銷處 | I34: DC店 | J34: SAL | K34: TW01088400 | L34: 金一電器有限公司 | M34: TW010884A1 | N34: 金一電器 | O34: TWSG003459 | P34: 金一電器(鳳坑村倉) | Q34: S | S34: DL004454-S | X34: TW012676 | Z34: 2213799* | AE34: 304 | AG34: 新竹縣新豐鄉鳳坑村15鄰649號 | AK34: TW | AL34: * 戴老闆 | AN34: M | AO34: X | AQ34: 2025.12.23 08:38:03 | AR34: 김승윤 seungyun2.kim@lgepartner.com | AS34: 2026.06.26 21:39:48 | AT34: 노용훈 yonghoon1.noh@lgepartner.com | AU34: EATT | AV34: [LGETT] Common | AW34: Domestic | AX34: 46014
A35: 錢亮均 | B35: 台北營銷處 | C35: 一般店 | E35: TW019189A1 | F35: 怡沃拉國際有限公司 | G35: LGETT | H35: 台北營銷處 | I35: 一般店 | J35: SAL | K35: TW01918900 | L35: 怡沃拉國際有限公司 | M35: TW019189A1 | N35: 怡沃拉國際有限公司 | O35: TWSG003647 | P35: 怡沃拉(汐止自助倉) | Q35: S | S35: DL004521-S | X35: TW012676 | Z35: 6057419* | AE35: 221 | AG35: 新北市汐止區汐萬路二段228巷18弄9 號 | AK35: TW | AL35: * | AN35: M | AO35: X | AQ35: 2026.05.20 08:00:06 | AR35: B_SS_ZZZZ001 | AS35: 2026.06.26 21:51:35 | AT35: 노용훈 yonghoon1.noh@lgepartner.com | AU35: EATT | AV35: [LGETT] Common | AW35: Domestic | AX35: 46162
A36: 趙鵬凱 | B36: AC Team | C36: 一般店 | E36: TW219474A1 | F36: 瑞鴻家電 | G36: AC Team | H36: AC TEAM | I36: 一般店 | J36: SAL | K36: TW21947400 | L36: 瑞鴻家電 | M36: TW219474A1 | N36: 瑞鴻家電 | O36: TWSG003510 | P36: 瑞鴻家電 | Q36: S | S36: TW007538-S | X36: TW012676 | Z36: 2486522* | AE36: 503 | AG36: 彰化縣花壇鄉花壇村番花路臨7號 | AK36: TW | AL36: 賴有勝 | AM36: 04-7863747 | AN36: M | AO36: X | AQ36: 2026.02.03 08:00:05 | AR36: B_SS_ZZZZ001 | AS36: 2026.06.26 21:51:39 | AT36: 노용훈 yonghoon1.noh@lgepartner.com | AU36: EATT | AV36: [LGETT] Common | AW36: Domestic | AX36: 46056
A37: 施漢鵬 | B37: MMCS | C37: 好市多_富基 | E37: TW019257A1 | F37: 富基電通 | G37: MM Part | H37: 好市多 | I37: 好市多_富基 | J37: SAL | K37: TW01370200 | L37: 富基電通股份有限公司 | M37: TW019257A1 | N37: 富基電通 | O37: TWSG003618 | P37: 富基-好市多(林口倉) | Q37: S | S37: MM000274-S | X37: TW012676 | Z37: 2752554* | AE37: 244 | AG37: 新北市林口區南勢里9鄰33-12號 | AK37: TW | AL37: * | AN37: M | AO37: X | AQ37: 2026.04.23 08:00:07 | AR37: B_SS_ZZZZ001 | AS37: 2026.06.26 21:56:18 | AT37: 노용훈 yonghoon1.noh@lgepartner.com | AU37: EATT | AV37: [LGETT] Common | AW37: Domestic | AX37: 46135
A38: 廖婉婷 | B38: B2B2C | C38: B2B2C | E38: TW019240A1 | F38: 映象國際 | G38: LGETT | H38: B2B2C(B2B2C Part) | I38: B2B2C | J38: SAL | K38: TW01427400 | L38: 映象國際企業有限公司 | M38: TW019240A1 | N38: 映象國際 | O38: TWSG003493 | P38: 映象國際 | Q38: S | S38: TW007943-S | X38: TW012676 | Z38: 2432316* | AE38: 100 | AG38: 台北市中正區中華一路一段25號2樓 | AK38: TW | AL38: 高慧娟 | AM38: 0939113292 | AN38: M | AO38: X | AQ38: 2026.01.23 08:00:07 | AR38: B_SS_ZZZZ001 | AS38: 2026.06.26 22:21:12 | AT38: 노용훈 yonghoon1.noh@lgepartner.com | AU38: EATT | AV38: [LGETT] Common | AW38: Domestic | AX38: 46045
A39: 錢亮均 | B39: 台北營銷處 | C39: 一般店 | E39: TW019207A1 | F39: 華綺電器有限公司 | G39: LGETT | H39: 台北營銷處 | I39: 一般店 | J39: SAL | K39: TW01920700 | L39: 華綺電器有限公司 | M39: TW019207A1 | N39: 華綺電器有限公司 | O39: TWSG003458 | P39: 華綺電器有限公司 | Q39: S | S39: TW007914-S | X39: TW012676 | Z39: 7067075* | AE39: 241 | AG39: 新北市三重區正義北路337號1樓 | AK39: TW | AL39: 王蕓菁 | AM39: 0963626892 | AN39: M | AO39: X | AQ39: 2025.12.23 08:38:40 | AR39: 김승윤 seungyun2.kim@lgepartner.com | AS39: 2026.06.26 22:21:12 | AT39: 노용훈 yonghoon1.noh@lgepartner.com | AU39: EATT | AV39: [LGETT] Common | AW39: Domestic | AX39: 46014
A40: 施漢鵬 | B40: MMCS | C40: 好市多 | E40: TW009133A1 | F40: 好市多股份有限公司 | G40: MM Dept. | H40: 好市多 | I40: 好市多 | J40: SAL | K40: TW00913300 | L40: 好巿多股份有限公司 | M40: TW009133A1 | N40: 好市多股份有限公司 | O40: TWSG003686 | P40: 好巿多股份有限公司(網購-商業配送) | Q40: S | X40: TW012676 | AE40: 333 | AG40: 桃園市龜山區頂湖路58號4樓 | AK40: TW | AL40: * | AN40: D | AO40: X | AQ40: 2026.07.07 17:29:45 | AR40: 김승윤 seungyun2.kim@lgepartner.com | AS40: 0000.00.00 00:00:00 | AU40: EATT | AV40: [LGETT] Common | AW40: Domestic | AX40: 46210
A41: 黃坤鎮 | B41: 嘉南營銷處 | C41: DC店 | E41: TW010291A1 | F41: 聯鈦冷凍空調電器行 | G41: Dealer Sales_ChiaNan Team | H41: 嘉南營銷處 | I41: DC店 | J41: SAL | K41: TW01029100 | L41: 聯鈦冷凍空調電器行陳裕仁 | M41: TW010291A1 | N41: 聯鈦冷凍空調電器行 | O41: TWSG001464 | P41: 聯鈦冷凍 | Q41: S | R41: Y | S41: TW002755 | X41: TW012676 | Z41: 1415633* | AE41: 640 | AG41: 雲林縣斗六市成功里成功路511號 | AK41: TW | AL41: 蕭淑梅 蕭淑梅. | AN41: M | AO41: X | AQ41: 2025.11.25 13:15:00 | AR41: 김승윤 seungyun2.kim@lgepartner.com | AS41: 2026.06.26 20:10:03 | AT41: 노용훈 yonghoon1.noh@lgepartner.com | AU41: EATT | AV41: [LGETT] Common | AW41: Domestic | AX41: 45986
A42: 陳志豐 | B42: 高屏營銷處 | C42: DC店 | E42: TW011013A1 | F42: 路得企業 | G42: Dealer Sales_KaoPing Team | H42: 高屏營銷處 | I42: DC店 | J42: SAL | K42: TW01101300 | L42: 路得企業有限公司 | M42: TW011013A1 | N42: 路得企業 | O42: TWSG000047 | P42: 路得企業 | Q42: S | R42: Y | S42: TW002083 | X42: TW012676 | Z42: 8467241* | AE42: 904 | AG42: 屏東縣九如鄉九如路二段304號1樓 | AK42: TW | AL42: 路得企業有限公司 路得企業有 | AN42: M | AO42: X | AQ42: 2025.11.25 13:15:02 | AR42: 김승윤 seungyun2.kim@lgepartner.com | AS42: 2026.06.26 20:24:50 | AT42: 노용훈 yonghoon1.noh@lgepartner.com | AU42: EATT | AV42: [LGETT] Common | AW42: Domestic | AX42: 45986
A43: 鄭鈞鴻 | B43: 台北營銷處 | C43: 一般店 | E43: TW010776A1 | F43: 瑞豪電器 | G43: Dealer Sales_Taipei Team | H43: 台北營銷處 | I43: 一般店 | J43: SAL | K43: TW01077600 | L43: 瑞豪電器行 | M43: TW010776A1 | N43: 瑞豪電器 | O43: TWSG000661 | P43: 瑞豪電器(送貨地址) | Q43: S | R43: Y | S43: DL000422 | X43: TW012676 | AE43: 266 | AG43: 宜蘭縣三星鄉三星路二段81號 | AK43: TW | AL43: 瑞豪電器行(送貨地址) | AN43: M | AO43: X | AQ43: 2025.11.25 13:14:55 | AR43: 김승윤 seungyun2.kim@lgepartner.com | AS43: 2026.06.26 20:51:27 | AT43: 노용훈 yonghoon1.noh@lgepartner.com | AU43: EATT | AV43: [LGETT] Common | AW43: Domestic | AX43: 45986
A44: 陳昱宏 | B44: MMCS | C44: 愛買 | E44: TW014433A1 | F44: 愛買吉安總公司 | G44: MM Part | H44: 愛買 | I44: 愛買 | J44: SAL | K44: TW01443300 | L44: 遠百企業股份有限公司 | M44: TW014433A1 | N44: 愛買吉安總公司 | O44: TWSG002345 | P44: 722愛買吉安彰化員林店 | Q44: S | R44: Y | S44: MM000071 | X44: TW012676 | Z44: 0571419* | AE44: 510 | AG44: 彰化縣員林鎮中正路2巷90號 | AK44: TW | AL44: 遠百企業股份有限公司(員林) | AN44: D | AO44: X | AQ44: 2025.11.25 14:58:26 | AR44: 정한석 hanseok.jung@lgepartner.com | AS44: 2026.06.26 21:06:10 | AT44: 노용훈 yonghoon1.noh@lgepartner.com | AU44: EATT | AV44: [LGETT] Common | AW44: Domestic | AX44: 45986
A45: 黃坤鎮 | B45: 嘉南營銷處 | C45: 一般店 | E45: TW011796A1 | F45: 欣益大企業 | G45: Dealer Sales_ChiaNan Team | H45: 嘉南營銷處 | I45: 一般店 | J45: SAL | K45: TW01179600 | L45: 欣益大企業有限公司 | M45: TW011796A1 | N45: 欣益大企業 | O45: TWSG001810 | P45: 欣益大企業 | Q45: S | S45: TW003169 | X45: TW012676 | Z45: 9741381* | AE45: 621 | AG45: 嘉義縣民雄鄉福樂村建國路三段132號1樓 | AK45: TW | AL45: 賴張麗雀 賴張麗雀. | AN45: M | AO45: X | AQ45: 2025.11.25 13:14:57 | AR45: 김승윤 seungyun2.kim@lgepartner.com | AS45: 2026.06.26 21:22:23 | AT45: 노용훈 yonghoon1.noh@lgepartner.com | AU45: EATT | AV45: [LGETT] Common | AW45: Domestic | AX45: 45986
A46: 黃坤鎮 | B46: 嘉南營銷處 | C46: 專售店 | E46: TW012269A1 | F46: 金樹電器空調 | G46: Dealer Sales_ChiaNan Team | H46: 嘉南營銷處 | I46: 專售店 | J46: SAL | K46: TW01226900 | L46: 金樹電器空調有限公司 | M46: TW012269A1 | N46: 金樹電器空調 | O46: TWSG000268 | P46: 金樹電器空調 | Q46: S | R46: Y | S46: TW003389 | X46: TW012676 | Z46: 8057249* | AE46: 632 | AG46: 雲林縣虎尾鎮德興里光復路563號1樓 | AK46: TW | AL46: 詹金樹 詹金樹. | AN46: M | AO46: X | AQ46: 2025.11.25 13:14:55 | AR46: 김승윤 seungyun2.kim@lgepartner.com | AS46: 2026.06.26 22:20:32 | AT46: 노용훈 yonghoon1.noh@lgepartner.com | AU46: EATT | AV46: [LGETT] Common | AW46: Domestic | AX46: 45986
A47: 陳緯峻 | B47: 台中營銷處 | C47: 一般店 | E47: TW014793A1 | F47: 鼎鋒國際 | G47: Dealer Sales_Taichung Team | H47: 台中營銷處 | I47: 一般店 | J47: SAL | K47: TW01479300 | L47: 鼎鋒國際有限公司 | M47: TW014793A1 | N47: 鼎鋒國際 | O47: TWSG000223 | P47: 鼎鋒國際 | Q47: S | R47: Y | S47: TW005279 | X47: TW012676 | Z47: 1625610* | AE47: 412 | AG47: 台中市大里區西榮里益民路二段326號1樓 | AK47: TW | AL47: 洪素? | AN47: D | AO47: X | AQ47: 2025.11.25 14:58:32 | AR47: 정한석 hanseok.jung@lgepartner.com | AS47: 2026.06.26 20:33:17 | AT47: 노용훈 yonghoon1.noh@lgepartner.com | AU47: EATT | AV47: [LGETT] Common | AW47: Domestic | AX47: 45986
A48: 陳勇志 | B48: MMCS | C48: 全聯 | E48: TW018313A1 | F48: 全聯 | G48: LGETT | H48: 全聯 | I48: 全聯 | J48: SAL | K48: TW01831300 | L48: 全聯 | M48: TW018313A1 | N48: 全聯 | O48: TWSG003153 | P48: 全聯(33八德店) | Q48: S | S48: MM000252-S | X48: TW012676 | Z48: 1674049* | AE48: 334 | AG48: 桃園市八德區介壽路二段148號 | AK48: TW | AL48: 全聯(33八德店) | AN48: M | AO48: X | AQ48: 2025.11.25 14:58:21 | AR48: 정한석 hanseok.jung@lgepartner.com | AS48: 2026.06.26 20:33:43 | AT48: 노용훈 yonghoon1.noh@lgepartner.com | AU48: EATT | AV48: [LGETT] Common | AW48: Domestic | AX48: 45986
A49: 施漢鵬 | B49: MMCS | C49: 特力屋 | E49: TW018429A1 | F49: 特力屋 | G49: CS Part | H49: 特力屋 | I49: 特力屋 | J49: SAL | K49: TW01842900 | L49: 特力屋股份有限公司 | M49: TW018429A1 | N49: 特力屋 | O49: TWSG002596 | P49: 特力屋-豐原店-FY | Q49: S | S49: CS001831-S | X49: TW012676 | Z49: 8939048* | AE49: 420 | AG49: 台中市豐原區南村里水源路420號 | AK49: TW | AL49: * | AN49: D | AO49: X | AQ49: 2025.11.25 14:58:36 | AR49: 정한석 hanseok.jung@lgepartner.com | AS49: 2026.06.26 21:06:24 | AT49: 노용훈 yonghoon1.noh@lgepartner.com | AU49: EATT | AV49: [LGETT] Common | AW49: Domestic | AX49: 45986
A50: 林威豪 | B50: 桃竹營銷處 | C50: 一般店 | E50: TW219432A1 | F50: 觀銘有限公司 | G50: Dealer Sales_TaoChu Team | H50: 桃竹營銷處 | I50: 一般店 | J50: SAL | K50: TW21943200 | L50: 觀銘有限公司 | M50: TW219432A1 | N50: 觀銘有限公司 | O50: TWSG003018 | P50: 觀銘有限公司(榮安街倉) | Q50: S | S50: DL004215-S | X50: TW012676 | Z50: 6960042* | AE50: 320 | AG50: 桃園市中壢區榮安十三街222號 | AK50: TW | AL50: * | AN50: D | AO50: X | AQ50: 2025.11.25 14:58:30 | AR50: 정한석 hanseok.jung@lgepartner.com | AS50: 2026.06.26 21:06:52 | AT50: 노용훈 yonghoon1.noh@lgepartner.com | AU50: EATT | AV50: [LGETT] Common | AW50: Domestic | AX50: 45986
A51: 胡智偉 | B51: 台中營銷處 | C51: 專售店 | E51: TW017579A1 | F51: 米米實業 | G51: Dealer Sales_Taichung Team | H51: 台中營銷處 | I51: 專售店 | J51: SAL | K51: TW01757900 | L51: 米米實業有限公司 | M51: TW017579A1 | N51: 米米實業 | O51: TWSG001578 | P51: 米米實業(穩達台北倉) | Q51: S | S51: DL003511 | X51: TW012676 | Z51: 5382171* | AE51: 244 | AG51: 新北市林口區菁埔1-58號 | AK51: TW | AL51: * 李三圳 | AN51: D | AO51: X | AQ51: 2025.11.25 14:58:22 | AR51: 정한석 hanseok.jung@lgepartner.com | AS51: 2026.06.26 21:07:07 | AT51: 노용훈 yonghoon1.noh@lgepartner.com | AU51: EATT | AV51: [LGETT] Common | AW51: Domestic | AX51: 45986
A52: 蔣承孝 | B52: 高屏營銷處 | C52: 一般店 | E52: TW219329A1 | F52: 首鑫家電有限公司 | G52: Dealer Sales_KaoPing Team | H52: 高屏營銷處 | I52: 一般店 | J52: SAL | K52: TW21932900 | L52: 首鑫家電有限公司 | M52: TW219329A1 | N52: 首鑫家電有限公司 | O52: TWSG000969 | P52: 首鑫家電(首席店) | Q52: S | S52: DL003928-S | X52: TW012676 | Z52: 2467268* | AE52: 820 | AG52: 高雄市岡山區柳橋東路25-5號 | AK52: TW | AL52: 店長:潘秀蕾 | AN52: D | AO52: X | AQ52: 2025.11.25 14:58:34 | AR52: 정한석 hanseok.jung@lgepartner.com | AS52: 2026.06.26 21:21:46 | AT52: 노용훈 yonghoon1.noh@lgepartner.com | AU52: EATT | AV52: [LGETT] Common | AW52: Domestic | AX52: 45986
A53: 顏豪志 | B53: 高屏營銷處 | C53: 一般店 | E53: TW219337A1 | F53: 睿凡企業 | G53: Dealer Sales_KaoPing Team | H53: 高屏營銷處 | I53: 一般店 | J53: SAL | K53: TW21933700 | L53: 睿凡企業 | M53: TW219337A1 | N53: 睿凡企業 | O53: TWSG001227 | P53: 睿凡企業 | Q53: S | R53: Y | S53: TW007223-S | X53: TW012676 | Z53: 5933851* | AE53: 804 | AG53: 高雄市鼓山區前峰里逢甲路５２號１樓 | AK53: TW | AL53: 楊祈銘 | AM53: 0920962388 | AN53: D | AO53: X | AQ53: 2025.11.25 14:58:32 | AR53: 정한석 hanseok.jung@lgepartner.com | AS53: 2026.06.26 21:27:17 | AT53: 노용훈 yonghoon1.noh@lgepartner.com | AU53: EATT | AV53: [LGETT] Common | AW53: Domestic | AX53: 45986
A54: 郭本威 | B54: OBS | C54: OBS | E54: TW219149A2 | F54: ONE TIME OBS | G54: OBS Team | H54: OBS | I54: OBS | J54: SAL | K54: TW21914900 | L54: ONE TIME OBS | M54: TW219149A2 | N54: ONE TIME OBS | O54: TWSG003260 | P54: ONE TIME OBS(B2B ID) | Q54: S | S54: DL003974-S | X54: TW012676 | Z54: 0000000* | AG54: * | AK54: TW | AL54: * | AN54: D | AO54: X | AQ54: 2025.11.25 14:58:29 | AR54: 정한석 hanseok.jung@lgepartner.com | AS54: 2026.06.26 21:38:09 | AT54: 노용훈 yonghoon1.noh@lgepartner.com | AU54: EATT | AV54: [LGETT] Common | AW54: Domestic | AX54: 45986
A55: #N/A | B55: #N/A | C55: ONLINE | E55: TW017185A1 | F55: 山淬股份有限公司 | G55: E-Commerce Team | H55: ONLINE | I55: ONLINE | J55: SAL | K55: TW01718500 | L55: 山淬股份有限公司 | M55: TW017185A1 | N55: 山淬股份有限公司 | O55: TWSG003020 | P55: 山淬股份有限公司(小家電) | Q55: S | S55: DL003802-S | X55: TW012676 | Z55: 5356318* | AE55: 247 | AG55: 新北市蘆洲區國道路2段86號2樓 (一樓碼頭) | AK55: TW | AL55: 梁宇帆 | AN55: D | AO55: X | AQ55: 2025.11.25 14:58:37 | AR55: 정한석 hanseok.jung@lgepartner.com | AS55: 2026.06.26 21:46:23 | AT55: 노용훈 yonghoon1.noh@lgepartner.com | AU55: EATT | AV55: [LGETT] Common | AW55: Domestic | AX55: 45986
A56: 粘棋欽 | B56: 嘉南營銷處 | C56: 一般店 | E56: TW013268A1 | F56: 王品電器 | G56: Dealer Sales_ChiaNan Team | H56: 嘉南營銷處 | I56: 一般店 | J56: SAL | K56: TW01326800 | L56: 王品電器有限公司 | M56: TW013268A1 | N56: 王品電器 | O56: TWSG001232 | P56: 王品(倉庫) | Q56: S | S56: DL001898 | X56: TW012676 | Z56: 2761001* | AE56: 726 | AG56: 台南市學甲區豐和里美豐80-2號 | AK56: TW | AL56: 王品電器有限公司(倉庫) | AN56: D | AO56: X | AQ56: 2025.11.25 14:58:30 | AR56: 정한석 hanseok.jung@lgepartner.com | AS56: 2026.06.26 21:46:27 | AT56: 노용훈 yonghoon1.noh@lgepartner.com | AU56: EATT | AV56: [LGETT] Common | AW56: Domestic | AX56: 45986
A57: 陳士騏 | B57: E-Commerce | C57: ONLINE | E57: TW219601A1 | F57: 展碁國際 | G57: E-Commerce Team | H57: ONLINE | I57: ONLINE | J57: SAL | K57: TW01204200 | L57: 展碁國際股份有限公司 | M57: TW219601A1 | N57: 展碁國際 | O57: TWSG001964 | P57: 展碁國際(高雄倉) | Q57: S | S57: DL003828-S | X57: TW012676 | Z57: 2077325* | AE57: 815 | AG57: 高雄市大社區保社甲路69號 | AK57: TW | AL57: 展碁國際(高雄倉) | AN57: D | AO57: X | AQ57: 2025.11.25 14:58:26 | AR57: 정한석 hanseok.jung@lgepartner.com | AS57: 2026.06.26 21:48:52 | AT57: 노용훈 yonghoon1.noh@lgepartner.com | AU57: EATT | AV57: [LGETT] Common | AW57: Domestic | AX57: 45986
A58: 吳睿涵 | B58: E-Commerce | C58: ONLINE | E58: TW219611A1 | F58: 欣福益行銷投資 | G58: E-Commerce Team | H58: ONLINE | I58: ONLINE | J58: SAL | K58: TW01894000 | L58: 欣福益行銷投資股份有限公司 | M58: TW219611A1 | N58: 欣福益行銷投資 | O58: TWSG001864 | P58: 欣福益行銷投資 | Q58: S | S58: TW007431-S | X58: TW012676 | Z58: 2485062* | AE58: 243 | AG58: 新北市泰山區山腳里泰林路2段332號 | AK58: TW | AL58: 陳郁昌 | AM58: 0933677369 | AN58: D | AO58: X | AQ58: 2025.11.25 14:58:30 | AR58: 정한석 hanseok.jung@lgepartner.com | AS58: 2026.06.26 21:52:19 | AT58: 노용훈 yonghoon1.noh@lgepartner.com | AU58: EATT | AV58: [LGETT] Common | AW58: Domestic | AX58: 45986
A59: 吳睿涵 | B59: E-Commerce | C59: ONLINE | E59: TW219323A1 | F59: 瑪黑家居選物 | G59: E-Commerce Team | H59: ONLINE | I59: ONLINE | J59: SAL | K59: TW21932300 | L59: 瑪黑家居選物 | M59: TW219323A1 | N59: 瑪黑家居選物 | O59: TWSG001853 | P59: 瑪黑家居選物(捷豐新倉) | Q59: S | S59: DL003953-S | X59: TW012676 | Z59: 5077224* | AE59: 338 | AG59: 桃園市蘆竹區海山中街75號 | AK59: TW | AL59: 林志修 | AM59: 0975410295 | AN59: D | AO59: X | AQ59: 2025.11.25 14:58:24 | AR59: 정한석 hanseok.jung@lgepartner.com | AS59: 2026.06.26 21:52:19 | AT59: 노용훈 yonghoon1.noh@lgepartner.com | AU59: EATT | AV59: [LGETT] Common | AW59: Domestic | AX59: 45986
A60: #N/A | B60: #N/A | C60: B2B2C | E60: TW018719A1 | F60: 德築生活科技 | G60: B2B2C Sales Part | H60: B2B2C(B2B2C Part) | I60: B2B2C | J60: SAL | K60: TW01871900 | L60: 德築生活科技股份有限公司 | M60: TW018719A1 | N60: 德築生活科技 | O60: TWSG001109 | P60: 德築生活科技 | Q60: S | R60: Y | S60: TW007488-S | X60: TW012676 | Z60: 4260002* | AE60: 265 | AG60: 宜蘭縣羅東鎮光榮路１１２號２樓 | AK60: TW | AL60: 黃瓊之 | AM60: 0983-920-528 | AN60: D | AO60: X | AQ60: 2025.11.25 14:58:34 | AR60: 정한석 hanseok.jung@lgepartner.com | AS60: 2026.06.26 21:56:33 | AT60: 노용훈 yonghoon1.noh@lgepartner.com | AU60: EATT | AV60: [LGETT] Common | AW60: Domestic | AX60: 45986
A61: 褚家鳴 | B61: 桃竹營銷處 | C61: 一般店 | E61: TW219523A1 | F61: 益碩空調工程行 | G61: Dealer Sales_TaoChu Team | H61: 桃竹營銷處 | I61: 一般店 | J61: SAL | K61: TW21952300 | L61: 益碩空調工程行 | M61: TW219523A1 | N61: 益碩空調工程行 | O61: TWSG001376 | P61: 益碩空調工程行 | Q61: S | R61: Y | S61: TW007627-S | X61: TW012676 | Z61: 3785220* | AE61: 310 | AG61: 新竹縣竹東鎮光明路556巷2號 | AK61: TW | AL61: * 鄭志雄 | AN61: D | AO61: X | AQ61: 2025.11.25 14:58:33 | AR61: 정한석 hanseok.jung@lgepartner.com | AS61: 2026.06.26 21:58:42 | AT61: 노용훈 yonghoon1.noh@lgepartner.com | AU61: EATT | AV61: [LGETT] Common | AW61: Domestic | AX61: 45986
A62: 顏豪志 | B62: 高屏營銷處 | C62: 一般店 | E62: TW219262A1 | F62: 立欣電器行 | G62: Dealer Sales_KaoPing Team | H62: 高屏營銷處 | I62: 一般店 | J62: SAL | K62: TW21926200 | L62: 立欣電器行 | M62: TW219262A1 | N62: 立欣電器行 | O62: TWSG001841 | P62: 立欣電器行(鳳山) | Q62: S | S62: DL003616-S | X62: TW012676 | Z62: 1025592* | AE62: 830 | AG62: 高雄市鳳山區甲智路160號 | AK62: TW | AL62: 方麗華 | AN62: D | AO62: X | AQ62: 2025.11.25 14:58:33 | AR62: 정한석 hanseok.jung@lgepartner.com | AS62: 2026.06.26 22:15:34 | AT62: 노용훈 yonghoon1.noh@lgepartner.com | AU62: EATT | AV62: [LGETT] Common | AW62: Domestic | AX62: 45986
A63: 褚家鳴 | B63: 桃竹營銷處 | C63: 一般店 | E63: TW010871A1 | F63: 皇典電器 | G63: Dealer Sales_TaoChu Team | H63: 桃竹營銷處 | I63: 一般店 | J63: SAL | K63: TW01087100 | L63: 皇典電器行 | M63: TW010871A1 | N63: 皇典電器 | O63: TWSG000187 | P63: 皇典電器行(龜山自租倉) | Q63: S | S63: DL004203-S | X63: TW012676 | Z63: 7854415* | AE63: 333 | AG63: 桃園市龜山區陳厝坑路997巷23號 | AK63: TW | AL63: * | AN63: D | AO63: X | AQ63: 2025.11.25 14:58:38 | AR63: 정한석 hanseok.jung@lgepartner.com | AS63: 2026.06.26 22:21:13 | AT63: 노용훈 yonghoon1.noh@lgepartner.com | AU63: EATT | AV63: [LGETT] Common | AW63: Domestic | AX63: 45986
A64: 顏豪志 | B64: 高屏營銷處 | C64: 專售店 | E64: TW019173A1 | F64: 樂嘉家電 | G64: Dealer Sales_KaoPing Team | H64: 高屏營銷處 | I64: 專售店 | J64: SAL | K64: TW01917300 | L64: 樂嘉家電 | M64: TW019173A1 | N64: 樂嘉家電 | O64: TWSG003200 | P64: 樂嘉家電(東源倉) | Q64: S | S64: DL004359-S | X64: TW012676 | Z64: 6058903* | AE64: 821 | AG64: 高雄市路竹區民族路132號 | AK64: TW | AL64: 樂嘉家電(東源倉) | AN64: M | AO64: X | AQ64: 2025.11.25 14:58:37 | AR64: 정한석 hanseok.jung@lgepartner.com | AS64: 2026.06.26 22:22:36 | AT64: 노용훈 yonghoon1.noh@lgepartner.com | AU64: EATT | AV64: [LGETT] Common | AW64: Domestic | AX64: 45986
A65: 李佶諹 | B65: 台中營銷處 | C65: 專售店 | E65: TW219298A1 | F65: 老王科技 | G65: Dealer Sales_Taichung Team | H65: 台中營銷處 | I65: 專售店 | J65: SAL | K65: TW21929800 | L65: 老王科技 | M65: TW219298A1 | N65: 老王科技 | O65: TWSG001837 | P65: 老王科技有限公司 | Q65: S | R65: Y | S65: TW007140-S | X65: TW012676 | Z65: 6330639* | AE65: 406 | AG65: 臺中市北屯區后庄里后庄北路２０２號３樓 | AK65: TW | AL65: 王炫盛 | AM65: 0953-351001 | AN65: M | AO65: X | AQ65: 2025.11.25 13:14:52 | AR65: 김승윤 seungyun2.kim@lgepartner.com | AS65: 2026.06.26 19:56:48 | AT65: 노용훈 yonghoon1.noh@lgepartner.com | AU65: EATT | AV65: [LGETT] Common | AW65: Domestic | AX65: 45986
A66: 李佶諹 | B66: 台中營銷處 | C66: 一般店 | E66: TW012774A1 | F66: 禾聲電器 | G66: Dealer Sales_Taichung Team | H66: 台中營銷處 | I66: 一般店 | J66: SAL | K66: TW01277400 | L66: 禾聲電器有限公司 | M66: TW012774A1 | N66: 禾聲電器 | O66: TWSG000980 | P66: 禾聲電器 | Q66: S | R66: Y | S66: TW004061 | X66: TW012676 | Z66: 9749927* | AE66: 406 | AG66: 台中市北屯區北屯路178之4號1樓 | AK66: TW | AL66: 許游明 | AN66: M | AO66: X | AQ66: 2025.11.25 13:15:00 | AR66: 김승윤 seungyun2.kim@lgepartner.com | AS66: 2026.06.26 20:02:46 | AT66: 노용훈 yonghoon1.noh@lgepartner.com | AU66: EATT | AV66: [LGETT] Common | AW66: Domestic | AX66: 45986
A67: 粘棋欽 | B67: 嘉南營銷處 | C67: 專售店 | E67: TW012380A1 | F67: 德豐電器 | G67: Dealer Sales_ChiaNan Team | H67: 嘉南營銷處 | I67: 專售店 | J67: SAL | K67: TW01238000 | L67: 德豐電器行 | M67: TW012380A1 | N67: 德豐電器 | O67: TWSG002427 | P67: 德豐電器 | Q67: S | R67: Y | S67: TW003760 | X67: TW012676 | Z67: 9887266* | AE67: 600 | AG67: 嘉義市東區安寮里世賢路4段456巷1號5樓之3 | AK67: TW | AL67: 鄭維寶 鄭維寶. | AN67: M | AO67: X | AQ67: 2025.11.25 13:14:57 | AR67: 김승윤 seungyun2.kim@lgepartner.com | AS67: 2026.06.26 22:20:18 | AT67: 노용훈 yonghoon1.noh@lgepartner.com | AU67: EATT | AV67: [LGETT] Common | AW67: Domestic | AX67: 45986
A68: 宋恩齊 | B68: 台中營銷處 | C68: 專售店 | E68: TW010664A1 | F68: 隆慶電器 | G68: Dealer Sales_Taichung Team | H68: 台中營銷處 | I68: 專售店 | J68: SAL | K68: TW01066400 | L68: 隆慶電器行 | M68: TW010664A1 | N68: 隆慶電器 | O68: TWSG001879 | P68: 隆慶電器 | Q68: S | R68: Y | S68: TW002851 | X68: TW012676 | Z68: 1993865* | AE68: 500 | AF68: 彰化縣 | AG68: 彰化縣彰化市一心東街149巷7號 | AK68: TW | AL68: 黃惠敏 | AN68: M | AO68: X | AQ68: 2025.11.25 13:15:00 | AR68: 김승윤 seungyun2.kim@lgepartner.com | AS68: 2026.06.26 22:20:36 | AT68: 노용훈 yonghoon1.noh@lgepartner.com | AU68: EATT | AV68: [LGETT] Common | AW68: Domestic | AX68: 45986
A69: 姜泊昆 | B69: IT Part | C69: IT | E69: TW219503A1 | F69: 新向系統科技 | G69: MS IT Sales Part | H69: IT | I69: IT | J69: SAL | K69: TW21950300 | L69: 新向系統科技 | M69: TW219503A1 | N69: 新向系統科技 | O69: TWSG002002 | P69: 新向系統科技 | Q69: S | S69: TW007578-S | X69: TW012676 | Z69: 2907697* | AE69: 231 | AG69: 新北市新店區安興路105號13樓 | AK69: TW | AL69: * 盧藝萱 | AN69: M | AO69: X | AQ69: 2025.11.25 13:14:50 | AR69: 김승윤 seungyun2.kim@lgepartner.com | AS69: 2026.06.26 22:23:36 | AT69: 노용훈 yonghoon1.noh@lgepartner.com | AU69: EATT | AV69: [LGETT] Common | AW69: Domestic | AX69: 45986
A70: 錢亮均 | B70: 台北營銷處 | C70: 專售店 | D70: AV店 | E70: TW013454A1 | F70: 祥建科技 | G70: Dealer Sales_Taipei Team | H70: 台北營銷處 | I70: 專售店 | J70: SAL | K70: TW01345400 | L70: 祥建科技股份有限公司 | M70: TW013454A1 | N70: 祥建科技 | O70: TWSG001183 | P70: 祥建(汐止) | Q70: S | S70: DL004051-S | X70: TW012676 | Z70: 2772473* | AE70: 221 | AG70: 新北市汐止區汐萬路2段228巷18弄9號 | AK70: TW | AL70: * 賴沈宗 | AN70: M | AO70: X | AQ70: 2025.11.25 13:14:58 | AR70: 김승윤 seungyun2.kim@lgepartner.com | AS70: 2026.07.08 13:42:18 | AT70: Chiajung Wu chiajung.wu@lge.com | AU70: EATT | AV70: [LGETT] Common | AW70: Domestic | AX70: 45986
A71: 林宜慧 | B71: E-Commerce | C71: ONLINE | E71: TW219546A1 | F71: 地標網通 | G71: E-Commerce Team | H71: ONLINE | I71: ONLINE | J71: SAL | K71: TW21954600 | L71: 地標網通 | M71: TW219546A1 | N71: 地標網通 | O71: TWSG002513 | P71: 地標網通(東源中宅) | Q71: S | S71: DL004218-S | X71: TW012676 | Z71: 2845980* | AE71: 414 | AG71: 台中市烏日區中山路三段130號 | AK71: TW | AL71: 陳芷涵 | AN71: M | AO71: X | AQ71: 2025.11.25 13:14:55 | AR71: 김승윤 seungyun2.kim@lgepartner.com | AS71: 2026.06.26 19:58:21 | AT71: 노용훈 yonghoon1.noh@lgepartner.com | AU71: EATT | AV71: [LGETT] Common | AW71: Domestic | AX71: 45986
A72: 粘棋欽 | B72: 嘉南營銷處 | C72: DC店 | E72: TW010951A1 | F72: 泰欣電器 | G72: Dealer Sales_ChiaNan Team | H72: 嘉南營銷處 | I72: DC店 | J72: SAL | K72: TW01095100 | L72: 泰欣電器行 | M72: TW010951A1 | N72: 泰欣電器 | O72: TWSG000360 | P72: 泰欣電器(民雄) | Q72: S | R72: Y | S72: DL003442-S | X72: TW012676 | Z72: 0655609* | AE72: 621 | AG72: 嘉義縣民雄鄉建國路3段260巷15號 | AK72: TW | AL72: * | AN72: M | AO72: X | AQ72: 2025.11.25 13:14:51 | AR72: 김승윤 seungyun2.kim@lgepartner.com | AS72: 2026.06.26 20:03:33 | AT72: 노용훈 yonghoon1.noh@lgepartner.com | AU72: EATT | AV72: [LGETT] Common | AW72: Domestic | AX72: 45986
A73: 徐華鈞 | B73: 桃竹營銷處 | C73: 專售店 | E73: TW018135A1 | F73: 姿芳科技有限公司 | G73: Dealer Sales_TaoChu Team | H73: 桃竹營銷處 | I73: 專售店 | J73: SAL | K73: TW01813500 | L73: 姿芳科技有限公司 | M73: TW018135A1 | N73: 姿芳科技有限公司 | O73: TWSG000134 | P73: 姿芳科技(佳事達自租倉) | Q73: S | S73: DL003943-S | X73: TW012676 | Z73: 4277090* | AE73: 333 | AG73: 桃園市龜山區陳厝坑路997巷23號 | AK73: TW | AL73: * | AN73: M | AO73: X | AQ73: 2025.11.25 13:15:00 | AR73: 김승윤 seungyun2.kim@lgepartner.com | AS73: 2026.06.26 20:03:38 | AT73: 노용훈 yonghoon1.noh@lgepartner.com | AU73: EATT | AV73: [LGETT] Common | AW73: Domestic | AX73: 45986
A74: 葉作仁 | B74: 桃竹營銷處 | C74: DC店 | E74: TW010845A1 | F74: 名富電器 | G74: Dealer Sales_TaoChu Team | H74: 桃竹營銷處 | I74: DC店 | J74: SAL | K74: TW01084500 | L74: 名富電器行 | M74: TW010845A1 | N74: 名富電器 | O74: TWSG000812 | P74: 名富電器(送貨地址) | Q74: S | S74: DL002451 | X74: TW012676 | Z74: 4516236* | AE74: 320 | AG74: 桃園縣中壢市中山東路1段40號 | AK74: TW | AL74: 名富電器行(送貨地址) | AN74: M | AO74: X | AQ74: 2025.11.25 13:14:59 | AR74: 김승윤 seungyun2.kim@lgepartner.com | AS74: 2026.06.26 20:19:58 | AT74: 노용훈 yonghoon1.noh@lgepartner.com | AU74: EATT | AV74: [LGETT] Common | AW74: Domestic | AX74: 45986
A75: 江柏慶 | B75: 嘉南營銷處 | C75: 專售店 | E75: TW014060A1 | F75: 東隆電器 | G75: Dealer Sales_ChiaNan Team | H75: 嘉南營銷處 | I75: 專售店 | J75: SAL | K75: TW01406000 | L75: 東隆電器有限公司 | M75: TW014060A1 | N75: 東隆電器 | O75: TWSG001358 | P75: 東隆電器(同興倉) | Q75: S | S75: DL003886-S | X75: TW012676 | Z75: 6939724* | AE75: 702 | AG75: 台南市南區同興路168巷151號 | AK75: TW | AL75: * 何文雅 | AM75: 0985991045 | AN75: M | AO75: X | AQ75: 2025.11.25 13:14:55 | AR75: 김승윤 seungyun2.kim@lgepartner.com | AS75: 2026.06.26 20:27:35 | AT75: 노용훈 yonghoon1.noh@lgepartner.com | AU75: EATT | AV75: [LGETT] Common | AW75: Domestic | AX75: 45986
A76: 陳緯峻 | B76: 台中營銷處 | C76: 一般店 | E76: TW011310A1 | F76: 匯豐家電 | G76: LGETT | H76: 台中營銷處 | I76: 一般店 | J76: SAL | K76: TW01131000 | L76: 匯豐家電有限公司 | M76: TW011310A1 | N76: 匯豐家電 | O76: TWSG000631 | P76: 匯豐家電 | Q76: S | R76: Y | S76: TW002978 | X76: TW012676 | Z76: 2383603* | AE76: 414 | AG76: 台中市烏日區中山路一段379號 | AK76: TW | AL76: 塗文村 塗文村. | AN76: M | AO76: X | AQ76: 2025.11.25 13:14:53 | AR76: 김승윤 seungyun2.kim@lgepartner.com | AS76: 2026.06.26 20:32:53 | AT76: 노용훈 yonghoon1.noh@lgepartner.com | AU76: EATT | AV76: [LGETT] Common | AW76: Domestic | AX76: 45986
A77: 錢亮均 | B77: 台北營銷處 | C77: 專售店 | E77: TW219533A1 | F77: 米米實業有限公司臺北分公司 | G77: Dealer Sales_Taipei Team | H77: 台北營銷處 | I77: 專售店 | J77: SAL | K77: TW01882500 | L77: 樂天行銷有限公司 | M77: TW018825A1 | N77: 樂天行銷有限公司 | O77: TWSG001612 | P77: 樂天觀音倉(MB) | Q77: S | S77: DL003956-S | X77: TW012676 | Z77: 4266341* | AE77: 328 | AG77: 桃園市觀音區中山路2段997號(左棟) | AH77: (週一到週五)上午09:00~11:50 下午13:30~15:00 | AK77: TW | AL77: * 吳思慧 | AN77: M | AO77: X | AQ77: 2025.11.25 13:14:53 | AR77: 김승윤 seungyun2.kim@lgepartner.com | AS77: 2026.06.26 20:32:54 | AT77: 노용훈 yonghoon1.noh@lgepartner.com | AU77: EATT | AV77: [LGETT] Common | AW77: Domestic | AX77: 45986
A78: 連承剛 | B78: 百貨 | C78: 百貨 | E78: TW014274A1 | F78: 映象國際 | G78: Department Store Team | H78: 百貨 | I78: 百貨 | J78: SAL | K78: TW01427400 | L78: 映象國際企業有限公司 | M78: TW014274A1 | N78: 映象國際 | O78: TWSG002235 | P78: 映象國際企業有限公司(南崁台茂) | Q78: S | S78: CS001626-S | X78: TW012676 | Z78: 2432316* | AE78: 338 | AG78: 桃園縣蘆竹鄉南崁路一段112號5樓 | AK78: TW | AL78: 黃柏智 | AN78: M | AO78: X | AQ78: 2025.11.25 13:14:57 | AR78: 김승윤 seungyun2.kim@lgepartner.com | AS78: 2026.06.26 20:50:32 | AT78: 노용훈 yonghoon1.noh@lgepartner.com | AU78: EATT | AV78: [LGETT] Common | AW78: Domestic | AX78: 45986
A79: 陳慶全 | B79: 台中營銷處 | C79: DC店 | E79: TW010905A1 | F79: 太子電業 | G79: Dealer Sales_Taichung Team | H79: 台中營銷處 | I79: DC店 | J79: SAL | K79: TW01090500 | L79: 太子電業行 | M79: TW010905A1 | N79: 太子電業 | O79: TWSG000081 | P79: 太子電業(鎮平倉) | Q79: S | S79: DL004174-S | X79: TW012676 | Z79: 7768533* | AE79: 436 | AG79: 台中市清水區鎮平路22-7號 | AK79: TW | AL79: * 簡巧宜 | AN79: M | AO79: X | AQ79: 2025.11.25 13:14:57 | AR79: 김승윤 seungyun2.kim@lgepartner.com | AS79: 2026.06.26 21:00:26 | AT79: 노용훈 yonghoon1.noh@lgepartner.com | AU79: EATT | AV79: [LGETT] Common | AW79: Domestic | AX79: 45986
A80: 錢亮均 | B80: 台北營銷處 | C80: 專售店 | E80: TW017542A1 | F80: 嘉豐電器 | G80: Dealer Sales_Taipei Team | H80: 台北營銷處 | I80: 專售店 | J80: SAL | K80: TW01754200 | L80: 嘉豐電器有限公司 | M80: TW017542A1 | N80: 嘉豐電器 | O80: TWSG000038 | P80: 嘉豐(教忠倉) | Q80: S | S80: DL004238-S | X80: TW012676 | Z80: 4510324* | AE80: 201 | AG80: 基隆市信義區教忠街119巷66號 | AK80: TW | AL80: * | AN80: M | AO80: X | AQ80: 2025.11.25 13:15:00 | AR80: 김승윤 seungyun2.kim@lgepartner.com | AS80: 2026.06.26 21:00:29 | AT80: 노용훈 yonghoon1.noh@lgepartner.com | AU80: EATT | AV80: [LGETT] Common | AW80: Domestic | AX80: 45986
A81: 李佶諹 | B81: 台中營銷處 | C81: 專售店 | E81: TW010761A1 | F81: 全民電子 | G81: Dealer Sales_Taichung Team | H81: 台中營銷處 | I81: 專售店 | J81: SAL | K81: TW01076100 | L81: 全民電子音響專賣店 | M81: TW010761A1 | N81: 全民電子 | O81: TWSG002346 | P81: 全民電子(西屯倉) | Q81: S | S81: DL004164-S | X81: TW012676 | Z81: 7759394* | AE81: 407 | AG81: 台中市西屯區工業區三十三路8-1號(東源物流) | AK81: TW | AL81: * | AN81: M | AO81: X | AQ81: 2025.11.25 13:14:51 | AR81: 김승윤 seungyun2.kim@lgepartner.com | AS81: 2026.06.26 21:06:11 | AT81: 노용훈 yonghoon1.noh@lgepartner.com | AU81: EATT | AV81: [LGETT] Common | AW81: Domestic | AX81: 45986
A82: 錢亮均 | B82: 台北營銷處 | C82: 一般店 | E82: TW219201A1 | F82: 明達電器 | G82: Dealer Sales_Taipei Team | H82: 台北營銷處 | I82: 一般店 | J82: SAL | K82: TW21920100 | L82: 明達電器 | M82: TW219201A1 | N82: 明達電器 | O82: TWSG000934 | P82: 明達電器 | Q82: S | R82: Y | S82: DL003436-S | X82: TW012676 | Z82: 1576423* | AE82: 242 | AG82: 新北市新莊區福樂街3號1樓 | AK82: TW | AL82: 明達電器行 | AN82: M | AO82: X | AQ82: 2025.11.25 13:14:48 | AR82: 김승윤 seungyun2.kim@lgepartner.com | AS82: 2026.06.26 21:06:17 | AT82: 노용훈 yonghoon1.noh@lgepartner.com | AU82: EATT | AV82: [LGETT] Common | AW82: Domestic | AX82: 45986
A83: 李思賢 | B83: 台中營銷處 | C83: 專售店 | E83: TW010646A1 | F83: 三信電氣 | G83: Dealer Sales_Taichung Team | H83: 台中營銷處 | I83: 專售店 | J83: SAL | K83: TW01064600 | L83: 三信電氣行 | M83: TW010646A1 | N83: 三信電氣 | O83: TWSG003265 | P83: 三信電氣(埔心南昌) | Q83: S | S83: DL004191-S | X83: TW012676 | Z83: 0835983* | AE83: 513 | AG83: 彰化縣埔心鄉南昌南路135巷23號 | AK83: TW | AL83: * | AN83: M | AO83: X | AQ83: 2025.11.25 13:14:51 | AR83: 김승윤 seungyun2.kim@lgepartner.com | AS83: 2026.06.26 21:06:25 | AT83: 노용훈 yonghoon1.noh@lgepartner.com | AU83: EATT | AV83: [LGETT] Common | AW83: Domestic | AX83: 45986
A84: 鄭鈞鴻 | B84: 台北營銷處 | C84: 一般店 | E84: TW219332A1 | F84: 正旺電器行 | G84: Dealer Sales_Taipei Team | H84: 台北營銷處 | I84: 一般店 | J84: SAL | K84: TW21933200 | L84: 正旺電器行 | M84: TW219332A1 | N84: 正旺電器行 | O84: TWSG001226 | P84: 正旺電器行 | Q84: S | R84: Y | S84: TW007216-S | X84: TW012676 | Z84: 8734911* | AE84: 975 | AG84: 花蓮縣鳳林鎮中正路二段169號 | AK84: TW | AL84: * 方怡婷 | AM84: 0975-362309 | AN84: M | AO84: X | AQ84: 2025.11.25 13:14:48 | AR84: 김승윤 seungyun2.kim@lgepartner.com | AS84: 2026.06.26 21:07:14 | AT84: 노용훈 yonghoon1.noh@lgepartner.com | AU84: EATT | AV84: [LGETT] Common | AW84: Domestic | AX84: 45986
A85: 沈勇良 | B85: 高屏營銷處 | C85: 一般店 | E85: TW016891A1 | F85: 正義電器有限公司 | G85: Dealer Sales_KaoPing Team | H85: 高屏營銷處 | I85: 一般店 | J85: SAL | K85: TW01689100 | L85: 正義電器有限公司 | M85: TW016891A1 | N85: 正義電器有限公司 | O85: TWSG003182 | P85: 正義電器有限公司 | Q85: S | R85: Y | S85: TW004541 | X85: TW012676 | Z85: 9715646* | AE85: 830 | AG85: 高雄市鳳山區自由路197號 | AK85: TW | AL85: 林清源 | AN85: M | AO85: X | AQ85: 2025.11.25 13:14:59 | AR85: 김승윤 seungyun2.kim@lgepartner.com | AS85: 2026.06.26 21:08:48 | AT85: 노용훈 yonghoon1.noh@lgepartner.com | AU85: EATT | AV85: [LGETT] Common | AW85: Domestic | AX85: 45986
A86: 褚家鳴 | B86: 桃竹營銷處 | C86: DC店 | D86: 批店 | E86: TW219231A1 | F86: 佳瑩科技有限公司 | G86: Dealer Sales_TaoChu Team | H86: 桃竹營銷處 | I86: DC店 | J86: SAL | K86: TW21923100 | L86: 佳瑩科技 | M86: TW219231A1 | N86: 佳瑩科技 | O86: TWSG000177 | P86: 佳瑩(新竹) | Q86: S | X86: TW012676 | Z86: 5328235* | AE86: 300 | AG86: 新竹市竹香南路206號 | AK86: TW | AL86: * | AN86: M | AO86: X | AQ86: 2025.11.25 13:14:49 | AR86: 김승윤 seungyun2.kim@lgepartner.com | AS86: 2026.06.26 21:09:56 | AT86: 노용훈 yonghoon1.noh@lgepartner.com | AU86: EATT | AV86: [LGETT] Common | AW86: Domestic | AX86: 45986
A87: 陳緯峻 | B87: 台中營銷處 | C87: DC店 | E87: TW219216A1 | F87: 洪昌企業社 | G87: Dealer Sales_Taichung Team | H87: 台中營銷處 | I87: DC店 | J87: SAL | K87: TW21921600 | L87: 洪昌企業社 | M87: TW219216A1 | N87: 洪昌企業社 | O87: TWSG001944 | P87: 洪昌企業社 | Q87: S | R87: Y | S87: TW006383-S | X87: TW012676 | Z87: 3883568* | AE87: 412 | AG87: 台中市大里區立仁里好來二街10號1F | AK87: TW | AL87: 洪子閔 | AM87: 04-2279-8079 | AN87: M | AO87: X | AQ87: 2025.11.25 13:14:58 | AR87: 김승윤 seungyun2.kim@lgepartner.com | AS87: 2026.06.26 21:15:02 | AT87: 노용훈 yonghoon1.noh@lgepartner.com | AU87: EATT | AV87: [LGETT] Common | AW87: Domestic | AX87: 45986
A88: 陳志豐 | B88: 高屏營銷處 | C88: 一般店 | E88: TW219176A1 | F88: 來福電器 | G88: Dealer Sales_KaoPing Team | H88: 高屏營銷處 | I88: 一般店 | J88: SAL | K88: TW21917600 | L88: 來福電器 | M88: TW219176A1 | N88: 來福電器 | O88: TWSG002009 | P88: 來福電器(送貨地址) | Q88: S | S88: DL003043 | X88: TW012676 | Z88: 0802678* | AE88: 900 | AG88: 屏東市廈門街68號 | AK88: TW | AL88: 方文正 | AN88: M | AO88: X | AQ88: 2025.11.25 13:14:50 | AR88: 김승윤 seungyun2.kim@lgepartner.com | AS88: 2026.06.26 21:21:49 | AT88: 노용훈 yonghoon1.noh@lgepartner.com | AU88: EATT | AV88: [LGETT] Common | AW88: Domestic | AX88: 45986
A89: 陳緯峻 | B89: 台中營銷處 | C89: 一般店 | E89: TW014773A1 | F89: 冠元電器行 | G89: Dealer Sales_Taichung Team | H89: 台中營銷處 | I89: 一般店 | J89: SAL | K89: TW01477300 | L89: 冠元電器行 | M89: TW014773A1 | N89: 冠元電器行 | O89: TWSG000532 | P89: 冠元電器(送貨地址) | Q89: S | S89: DL003178 | X89: TW012676 | Z89: 1373627* | AE89: 507 | AG89: 彰化縣線西鄉沿海一段728巷139號 | AK89: TW | AL89: 冠元電器行(送貨地址) | AN89: M | AO89: X | AQ89: 2025.11.25 13:14:55 | AR89: 김승윤 seungyun2.kim@lgepartner.com | AS89: 2026.06.26 21:22:29 | AT89: 노용훈 yonghoon1.noh@lgepartner.com | AU89: EATT | AV89: [LGETT] Common | AW89: Domestic | AX89: 45986
A90: 楊淳 | B90: 台北營銷處 | C90: 專售店 | E90: TW018727A1 | F90: 三瀛實業有限公司 | G90: Dealer Sales_Taipei Team | H90: 台北營銷處 | I90: 專售店 | J90: SAL | K90: TW01872700 | L90: 三瀛實業有限公司 | M90: TW018727A1 | N90: 三瀛實業有限公司 | O90: TWSG001224 | P90: 三瀛創意營銷有限公司 | Q90: S | R90: Y | S90: TW007217-S | X90: TW012676 | Z90: 5275180* | AE90: 231 | AG90: 新北市新店區安康路二段20號1樓 | AK90: TW | AL90: * 強家燊 | AN90: M | AO90: X | AQ90: 2025.11.25 13:14:58 | AR90: 김승윤 seungyun2.kim@lgepartner.com | AS90: 2026.06.26 21:27:18 | AT90: 노용훈 yonghoon1.noh@lgepartner.com | AU90: EATT | AV90: [LGETT] Common | AW90: Domestic | AX90: 45986
A91: 李思賢 | B91: 台中營銷處 | C91: DC店 | E91: TW219419A1 | F91: 沅和科技 | G91: Dealer Sales_Taichung Team | H91: 台中營銷處 | I91: DC店 | J91: SAL | K91: TW21941900 | L91: 沅和科技 | M91: TW219419A1 | N91: 沅和科技 | O91: TWSG002054 | P91: 沅和科技 | Q91: S | R91: Y | S91: TW007455-S | X91: TW012676 | Z91: 9019156* | AE91: 542 | AG91: 南投縣草屯鎮南埔里中正路253之25巷17號 | AK91: TW | AL91: 曹珮菁 | AN91: M | AO91: X | AQ91: 2025.11.25 13:15:00 | AR91: 김승윤 seungyun2.kim@lgepartner.com | AS91: 2026.06.26 21:44:49 | AT91: 노용훈 yonghoon1.noh@lgepartner.com | AU91: EATT | AV91: [LGETT] Common | AW91: Domestic | AX91: 45986
A92: 粘棋欽 | B92: 嘉南營銷處 | C92: 一般店 | E92: TW219192A1 | F92: 九龍電器 | G92: Dealer Sales_ChiaNan Team | H92: 嘉南營銷處 | I92: 一般店 | J92: SAL | K92: TW21919200 | L92: 九龍電器 | M92: TW219192A1 | N92: 九龍電器 | O92: TWSG001511 | P92: 九龍電器 | Q92: S | R92: Y | S92: TW003234 | X92: TW012676 | Z92: 0619305* | AE92: 651 | AG92: 雲林縣北港鎮文化路95號 | AK92: TW | AL92: 吳正旭 吳正旭. | AN92: M | AO92: X | AQ92: 2025.11.25 13:14:48 | AR92: 김승윤 seungyun2.kim@lgepartner.com | AS92: 2026.06.26 21:46:36 | AT92: 노용훈 yonghoon1.noh@lgepartner.com | AU92: EATT | AV92: [LGETT] Common | AW92: Domestic | AX92: 45986
A93: 江柏慶 | B93: 嘉南營銷處 | C93: 一般店 | E93: TW018636A1 | F93: 日進電器 | G93: Dealer Sales_ChiaNan Team | H93: 嘉南營銷處 | I93: 一般店 | J93: SAL | K93: TW01863600 | L93: 日進電器有限公司 | M93: TW018636A1 | N93: 日進電器 | O93: TWSG000854 | P93: 日進電器(東區本店) | Q93: S | S93: DL004077-S | X93: TW012676 | Z93: 5328226* | AE93: 701 | AG93: 台南市東區德昌路196巷1號 | AK93: TW | AL93: * 王湘蓉 | AN93: M | AO93: X | AQ93: 2025.11.25 13:14:53 | AR93: 김승윤 seungyun2.kim@lgepartner.com | AS93: 2026.06.26 21:48:46 | AT93: 노용훈 yonghoon1.noh@lgepartner.com | AU93: EATT | AV93: [LGETT] Common | AW93: Domestic | AX93: 45986
A94: 李思賢 | B94: 台中營銷處 | C94: 一般店 | E94: TW219244A1 | F94: 東家電器行 | G94: Dealer Sales_Taichung Team | H94: 台中營銷處 | I94: 一般店 | J94: SAL | K94: TW01707000 | L94: 東洋電器行 | M94: TW017070A1 | N94: 東洋電器行 | O94: TWSG001941 | P94: 東洋電器(倉庫) | Q94: S | S94: DL003449-S | X94: TW012676 | Z94: 3888135* | AE94: 542 | AG94: 南投縣草屯鎮民生一街46巷6號 | AK94: TW | AL94: * | AN94: M | AO94: X | AQ94: 2025.11.25 13:15:00 | AR94: 김승윤 seungyun2.kim@lgepartner.com | AS94: 2026.06.26 21:56:12 | AT94: 노용훈 yonghoon1.noh@lgepartner.com | AU94: EATT | AV94: [LGETT] Common | AW94: Domestic | AX94: 45986
A95: 鄭鈞鴻 | B95: 台北營銷處 | C95: 一般店 | E95: TW014812A1 | F95: 太夆音響 | G95: Dealer Sales_Taipei Team | H95: 台北營銷處 | I95: 一般店 | J95: SAL | K95: TW01481200 | L95: 太夆音響電業行 | M95: TW014812A1 | N95: 太夆音響 | O95: TWSG000351 | P95: 太夆音響 | Q95: S | R95: Y | S95: TW005475-S | X95: TW012676 | Z95: 3020947* | AE95: 970 | AG95: 花蓮市中華路335-1號1樓 | AK95: TW | AL95: 鄭琮翰 | AN95: M | AO95: X | AQ95: 2025.11.25 13:14:49 | AR95: 김승윤 seungyun2.kim@lgepartner.com | AS95: 2026.06.26 21:56:23 | AT95: 노용훈 yonghoon1.noh@lgepartner.com | AU95: EATT | AV95: [LGETT] Common | AW95: Domestic | AX95: 45986
A96: 李佶諹 | B96: 台中營銷處 | C96: 一般店 | E96: TW219484A1 | F96: 居佳適家電 | G96: Dealer Sales_Taichung Team | H96: 台中營銷處 | I96: 一般店 | J96: SAL | K96: TW21948400 | L96: 居佳適家電 | M96: TW219484A1 | N96: 居佳適家電 | O96: TWSG000471 | P96: 居佳適 | Q96: S | R96: Y | S96: TW007555-S | X96: TW012676 | Z96: 8851492* | AE96: 411 | AG96: 台中市太平區七星路127號 | AK96: TW | AL96: * 江巧琳 | AN96: M | AO96: X | AQ96: 2025.11.25 13:14:57 | AR96: 김승윤 seungyun2.kim@lgepartner.com | AS96: 2026.06.26 21:58:34 | AT96: 노용훈 yonghoon1.noh@lgepartner.com | AU96: EATT | AV96: [LGETT] Common | AW96: Domestic | AX96: 45986
A97: 施漢鵬 | B97: MMCS | C97: 好市多 | E97: TW018542A1 | F97: 好市多股份有限公司北台中分公司 | G97: MM Dept. | H97: 好市多 | I97: 好市多 | J97: SAL | K97: TW01854200 | L97: 好市多股份有限公司北台中分公司 | M97: TW018542A1 | N97: 好市多股份有限公司北台中分公司 | O97: TWSG000782 | P97: 好市多股份有限公司北台中分公司 | Q97: S | S97: TW007200-S | X97: TW012676 | Z97: 8379447* | AE97: 406 | AG97: 台中市北屯區舊社里1鄰 敦富路 366、368 號 | AK97: TW | AL97: * | AN97: M | AO97: X | AQ97: 2025.11.25 13:14:55 | AR97: 김승윤 seungyun2.kim@lgepartner.com | AS97: 2026.06.26 21:58:40 | AT97: 노용훈 yonghoon1.noh@lgepartner.com | AU97: EATT | AV97: [LGETT] Common | AW97: Domestic | AX97: 45986
A98: 錢亮均 | B98: 台北營銷處 | C98: 專售店 | E98: TW016379A1 | F98: 上晟國際 | G98: Dealer Sales_Taipei Team | H98: 台北營銷處 | I98: 專售店 | J98: SAL | K98: TW01637900 | L98: 上晟國際有限公司 | M98: TW016379A1 | N98: 上晟國際 | O98: TWSG000905 | P98: 上晟(三重店) | Q98: S | S98: DL003998-S | X98: TW012676 | Z98: 5333522* | AE98: 241 | AG98: 新北市三重區自強路一段225號 | AK98: TW | AL98: * | AN98: M | AO98: X | AQ98: 2025.11.25 13:14:57 | AR98: 김승윤 seungyun2.kim@lgepartner.com | AS98: 2026.06.26 22:12:13 | AT98: 노용훈 yonghoon1.noh@lgepartner.com | AU98: EATT | AV98: [LGETT] Common | AW98: Domestic | AX98: 45986
A99: 葉作仁 | B99: 桃竹營銷處 | C99: 一般店 | E99: TW012990A1 | F99: 旭聲電器 | G99: Dealer Sales_TaoChu Team | H99: 桃竹營銷處 | I99: 一般店 | J99: SAL | K99: TW01299000 | L99: 旭聲電器行 | M99: TW012990A1 | N99: 旭聲電器 | O99: TWSG003202 | P99: 旭聲電器行(永美路) | Q99: S | S99: DL004361-S | X99: TW012676 | Z99: 8793566* | AE99: 326 | AG99: 桃園市楊梅區永美路151號1樓 | AK99: TW | AL99: * 廖婕羽 | AN99: M | AO99: X | AQ99: 2025.11.25 13:14:53 | AR99: 김승윤 seungyun2.kim@lgepartner.com | AS99: 2026.06.26 22:16:01 | AT99: 노용훈 yonghoon1.noh@lgepartner.com | AU99: EATT | AV99: [LGETT] Common | AW99: Domestic | AX99: 45986
A100: #N/A | B100: #N/A | E100: TW017207A1 | F100: 李師傅企業社 | G100: LGETT | H100: SVC | J100: SAL | K100: TW01720700 | L100: 李師傅企業社 | M100: TW017207A1 | N100: 李師傅企業社 | O100: TWSG000837 | P100: 李師傅企業社 | Q100: S | X100: TW012676 | Z100: 4072216* | AC100: 台南市 | AE100: 702 | AF100: 台南市 | AG100: 南區永成路2段501-2號 | AK100: TW | AL100: 李信村 | AN100: M | AO100: X | AQ100: 2025.11.25 13:15:02 | AR100: 김승윤 seungyun2.kim@lgepartner.com | AS100: 2026.07.13 15:01:33 | AT100: Wenhao Lee wenhao.lee@lge.com | AU100: EATT | AV100: [LGETT] Common | AW100: Domestic | AX100: 45986
...

Sheet 業務員
A1: Status | B1: Icon | C1: Sales Org. | D1: Dist.Ch. | E1: Distr.Type. | F1: Sold-To Party | G1: Sold-To Name | H1: Ship-To Party | I1: Ship-To Party Name | J1: Salesperson | K1: Salesperson Name | L1: Resignation Flag | M1: Resignation | N1: Department Code | O1: Department Name | P1: Dept. BA | Q1: Division | R1: Department Type | S1: Start Date | T1: End Date | U1: Security Dept.Code | V1: Security Dept. | W1: Inactive | X1: Created By | Y1: Created On | Z1: Created At | AA1: Changed By | AB1: Changed On | AC1: Changed At | AD1: Message | AE1: 業務員 | AF1: 業務員單位
C2: TT00 | D2: 10 | E2: OM | F2: TW019228A1 | G2: 億電通國際 | J2: TT001518 | K2: 羅 時景 | L2: A | M2: Active | N2: 12104017 | O2: LGETT Co-President | P2: SAL | R2: STAFF | S2: 46038 | T2: 401769 | U2: 11000151 | V2: LGETT | W2: false | X2: changsun.yang_chang sun Yang | Y2: 46203 | Z2: 0.80075231 | AA2: changsun.yang_chang sun Yang | AB2: 46203 | AC2: 0.80075231 | AE2: =IFERROR(VLOOKUP(J2&K2,對照!A:C,2,0),"") -> 羅時景 | AF2: =IFERROR(VLOOKUP(J2&K2,對照!A:C,3,0),"") -> ETC
C3: TT00 | D3: 10 | E3: OM | F3: TW019228A1 | G3: 億電通國際 | H3: TWSG003472 | I3: 億電通國際 | J3: TT001518 | K3: 羅 時景 | L3: A | M3: Active | N3: 12104017 | O3: LGETT Co-President | P3: SAL | R3: STAFF | S3: 46038 | T3: 401769 | U3: 11000151 | V3: LGETT | W3: false | X3: changsun.yang_chang sun Yang | Y3: 46203 | Z3: 0.80075231 | AA3: changsun.yang_chang sun Yang | AB3: 46203 | AC3: 0.80075231 | AE3: =IFERROR(VLOOKUP(J3&K3,對照!A:C,2,0),"") -> 羅時景 | AF3: =IFERROR(VLOOKUP(J3&K3,對照!A:C,3,0),"") -> ETC
C4: TT00 | D4: 10 | E4: OM | F4: TW219504A1 | G4: 九三商行 | J4: TT001518 | K4: 羅 時景 | L4: A | M4: Active | N4: 12104017 | O4: LGETT Co-President | P4: SAL | R4: STAFF | S4: 46038 | T4: 401769 | U4: 11000151 | V4: LGETT | W4: false | X4: changsun.yang_chang sun Yang | Y4: 46203 | Z4: 0.80075231 | AA4: changsun.yang_chang sun Yang | AB4: 46203 | AC4: 0.80075231 | AE4: =IFERROR(VLOOKUP(J4&K4,對照!A:C,2,0),"") -> 羅時景 | AF4: =IFERROR(VLOOKUP(J4&K4,對照!A:C,3,0),"") -> ETC
C5: TT00 | D5: 10 | E5: OM | F5: TW019311A1 | G5: 捷超工程行 | J5: TT230597 | K5: 顏 豪志 | L5: A | M5: Active | N5: 11007247 | O5: Dealer Sales_KaoPing Team | P5: SAL | R5: SALES | S5: 46252 | T5: 2958465 | U5: 11000151 | V5: LGETT | W5: false | X5: yuchin.chen_Yuchin Chen | Y5: 46252 | Z5: 0.41643519 | AA5: yuchin.chen_Yuchin Chen | AB5: 46252 | AC5: 0.41643519 | AE5: =IFERROR(VLOOKUP(J5&K5,對照!A:C,2,0),"") -> 顏豪志 | AF5: =IFERROR(VLOOKUP(J5&K5,對照!A:C,3,0),"") -> 高屏營銷處
C6: TT00 | D6: 10 | E6: OM | F6: TW018773A1 | G6: 集盛股份有限公司 | H6: TWSG000389 | I6: 集盛(股)公司(東源湖內) | J6: TT230597 | K6: 顏 豪志 | L6: A | M6: Active | N6: 11007247 | O6: Dealer Sales_KaoPing Team | P6: SAL | R6: SALES | S6: 46219 | T6: 2958465 | U6: 11000151 | V6: LGETT | W6: false | X6: yuchin.chen_Yuchin Chen | Y6: 46219 | Z6: 0.68414352 | AA6: yuchin.chen_Yuchin Chen | AB6: 46219 | AC6: 0.68414352 | AE6: =IFERROR(VLOOKUP(J6&K6,對照!A:C,2,0),"") -> 顏豪志 | AF6: =IFERROR(VLOOKUP(J6&K6,對照!A:C,3,0),"") -> 高屏營銷處
C7: TT00 | D7: 10 | E7: OM | F7: TW014723A1 | G7: 翠亨企業 | H7: TW014723 | I7: 翠亨企業股份有限公司 | J7: TT230597 | K7: 顏 豪志 | L7: A | M7: Active | N7: 11007247 | O7: Dealer Sales_KaoPing Team | P7: SAL | R7: SALES | S7: 46204 | T7: 401769 | U7: 11000151 | V7: LGETT | W7: false | X7: changsun.yang_chang sun Yang | Y7: 46203 | Z7: 0.80075231 | AA7: changsun.yang_chang sun Yang | AB7: 46203 | AC7: 0.80075231 | AE7: =IFERROR(VLOOKUP(J7&K7,對照!A:C,2,0),"") -> 顏豪志 | AF7: =IFERROR(VLOOKUP(J7&K7,對照!A:C,3,0),"") -> 高屏營銷處
C8: TT00 | D8: 10 | E8: OM | F8: TW014723A1 | G8: 翠亨企業 | H8: TWSG002474 | I8: 翠亨企業(路竹倉) | J8: TT230597 | K8: 顏 豪志 | L8: A | M8: Active | N8: 11007247 | O8: Dealer Sales_KaoPing Team | P8: SAL | R8: SALES | S8: 46204 | T8: 401769 | U8: 11000151 | V8: LGETT | W8: false | X8: changsun.yang_chang sun Yang | Y8: 46203 | Z8: 0.80075231 | AA8: changsun.yang_chang sun Yang | AB8: 46203 | AC8: 0.80075231 | AE8: =IFERROR(VLOOKUP(J8&K8,對照!A:C,2,0),"") -> 顏豪志 | AF8: =IFERROR(VLOOKUP(J8&K8,對照!A:C,3,0),"") -> 高屏營銷處
C9: TT00 | D9: 10 | E9: OM | F9: TW014723A1 | G9: 翠亨企業 | J9: TT230597 | K9: 顏 豪志 | L9: A | M9: Active | N9: 11007247 | O9: Dealer Sales_KaoPing Team | P9: SAL | R9: SALES | S9: 46204 | T9: 401769 | U9: 11000151 | V9: LGETT | W9: false | X9: changsun.yang_chang sun Yang | Y9: 46203 | Z9: 0.80075231 | AA9: changsun.yang_chang sun Yang | AB9: 46203 | AC9: 0.80075231 | AE9: =IFERROR(VLOOKUP(J9&K9,對照!A:C,2,0),"") -> 顏豪志 | AF9: =IFERROR(VLOOKUP(J9&K9,對照!A:C,3,0),"") -> 高屏營銷處
C10: TT00 | D10: 10 | E10: OM | F10: TW219262A1 | G10: 立欣電器行 | J10: TT230597 | K10: 顏 豪志 | L10: A | M10: Active | N10: 11007247 | O10: Dealer Sales_KaoPing Team | P10: SAL | R10: SALES | S10: 46204 | T10: 401769 | U10: 11000151 | V10: LGETT | W10: false | X10: changsun.yang_chang sun Yang | Y10: 46203 | Z10: 0.80075231 | AA10: changsun.yang_chang sun Yang | AB10: 46203 | AC10: 0.80075231 | AE10: =IFERROR(VLOOKUP(J10&K10,對照!A:C,2,0),"") -> 顏豪志 | AF10: =IFERROR(VLOOKUP(J10&K10,對照!A:C,3,0),"") -> 高屏營銷處
C11: TT00 | D11: 10 | E11: OM | F11: TW219540A1 | G11: 弘力電器行 | J11: TT230597 | K11: 顏 豪志 | L11: A | M11: Active | N11: 11007247 | O11: Dealer Sales_KaoPing Team | P11: SAL | R11: SALES | S11: 46204 | T11: 401769 | U11: 11000151 | V11: LGETT | W11: false | X11: changsun.yang_chang sun Yang | Y11: 46203 | Z11: 0.80075231 | AA11: changsun.yang_chang sun Yang | AB11: 46203 | AC11: 0.80075231 | AE11: =IFERROR(VLOOKUP(J11&K11,對照!A:C,2,0),"") -> 顏豪志 | AF11: =IFERROR(VLOOKUP(J11&K11,對照!A:C,3,0),"") -> 高屏營銷處
C12: TT00 | D12: 10 | E12: OM | F12: TW014331A1 | G12: 上眾電器 | H12: TWSG003666 | I12: 上眾(新生倉庫) | J12: TT230597 | K12: 顏 豪志 | L12: A | M12: Active | N12: 11007247 | O12: Dealer Sales_KaoPing Team | P12: SAL | R12: SALES | S12: 46196 | T12: 401769 | U12: 11000151 | V12: LGETT | W12: false | X12: changsun.yang_chang sun Yang | Y12: 46203 | Z12: 0.80075231 | AA12: changsun.yang_chang sun Yang | AB12: 46203 | AC12: 0.80075231 | AE12: =IFERROR(VLOOKUP(J12&K12,對照!A:C,2,0),"") -> 顏豪志 | AF12: =IFERROR(VLOOKUP(J12&K12,對照!A:C,3,0),"") -> 高屏營銷處
C13: TT00 | D13: 10 | E13: OM | F13: TW018785A1 | G13: 羅森數位有限公司 | J13: TT230597 | K13: 顏 豪志 | L13: A | M13: Active | N13: 11007247 | O13: Dealer Sales_KaoPing Team | P13: SAL | R13: SALES | S13: 46124 | T13: 401769 | U13: 11000151 | V13: LGETT | W13: false | X13: changsun.yang_chang sun Yang | Y13: 46203 | Z13: 0.80075231 | AA13: changsun.yang_chang sun Yang | AB13: 46203 | AC13: 0.80075231 | AE13: =IFERROR(VLOOKUP(J13&K13,對照!A:C,2,0),"") -> 顏豪志 | AF13: =IFERROR(VLOOKUP(J13&K13,對照!A:C,3,0),"") -> 高屏營銷處
C14: TT00 | D14: 10 | E14: OM | F14: TW018785A1 | G14: 羅森數位有限公司 | H14: TWSG001992 | I14: 羅森數位(仁武倉) | J14: TT230597 | K14: 顏 豪志 | L14: A | M14: Active | N14: 11007247 | O14: Dealer Sales_KaoPing Team | P14: SAL | R14: SALES | S14: 46124 | T14: 401769 | U14: 11000151 | V14: LGETT | W14: false | X14: changsun.yang_chang sun Yang | Y14: 46203 | Z14: 0.80075231 | AA14: changsun.yang_chang sun Yang | AB14: 46203 | AC14: 0.80075231 | AE14: =IFERROR(VLOOKUP(J14&K14,對照!A:C,2,0),"") -> 顏豪志 | AF14: =IFERROR(VLOOKUP(J14&K14,對照!A:C,3,0),"") -> 高屏營銷處
C15: TT00 | D15: 10 | E15: OM | F15: TW018785A1 | G15: 羅森數位有限公司 | H15: TWSG003518 | I15: 羅森數位(佳事達自租倉) | J15: TT230597 | K15: 顏 豪志 | L15: A | M15: Active | N15: 11007247 | O15: Dealer Sales_KaoPing Team | P15: SAL | R15: SALES | S15: 46124 | T15: 401769 | U15: 11000151 | V15: LGETT | W15: false | X15: changsun.yang_chang sun Yang | Y15: 46203 | Z15: 0.80075231 | AA15: changsun.yang_chang sun Yang | AB15: 46203 | AC15: 0.80075231 | AE15: =IFERROR(VLOOKUP(J15&K15,對照!A:C,2,0),"") -> 顏豪志 | AF15: =IFERROR(VLOOKUP(J15&K15,對照!A:C,3,0),"") -> 高屏營銷處
C16: TT00 | D16: 10 | E16: OM | F16: TW219261A1 | G16: 允丞電器 | J16: TT230597 | K16: 顏 豪志 | L16: A | M16: Active | N16: 11007247 | O16: Dealer Sales_KaoPing Team | P16: SAL | R16: SALES | S16: 46123 | T16: 401769 | U16: 11000151 | V16: LGETT | W16: false | X16: changsun.yang_chang sun Yang | Y16: 46203 | Z16: 0.80075231 | AA16: changsun.yang_chang sun Yang | AB16: 46203 | AC16: 0.80075231 | AE16: =IFERROR(VLOOKUP(J16&K16,對照!A:C,2,0),"") -> 顏豪志 | AF16: =IFERROR(VLOOKUP(J16&K16,對照!A:C,3,0),"") -> 高屏營銷處
C17: TT00 | D17: 10 | E17: OM | F17: TW219317A1 | G17: 九九電器工程 | J17: TT230597 | K17: 顏 豪志 | L17: A | M17: Active | N17: 11007247 | O17: Dealer Sales_KaoPing Team | P17: SAL | R17: SALES | S17: 46123 | T17: 401769 | U17: 11000151 | V17: LGETT | W17: false | X17: changsun.yang_chang sun Yang | Y17: 46203 | Z17: 0.80075231 | AA17: changsun.yang_chang sun Yang | AB17: 46203 | AC17: 0.80075231 | AE17: =IFERROR(VLOOKUP(J17&K17,對照!A:C,2,0),"") -> 顏豪志 | AF17: =IFERROR(VLOOKUP(J17&K17,對照!A:C,3,0),"") -> 高屏營銷處
C18: TT00 | D18: 10 | E18: OM | F18: TW019173A1 | G18: 樂嘉家電 | H18: TWSG003198 | I18: 樂嘉家電(秀翔瑞揚倉) | J18: TT230597 | K18: 顏 豪志 | L18: A | M18: Active | N18: 11007247 | O18: Dealer Sales_KaoPing Team | P18: SAL | R18: SALES | S18: 45909 | T18: 401769 | U18: 11000151 | V18: LGETT | W18: false | X18: changsun.yang_chang sun Yang | Y18: 46203 | Z18: 0.80075231 | AA18: changsun.yang_chang sun Yang | AB18: 46203 | AC18: 0.80075231 | AE18: =IFERROR(VLOOKUP(J18&K18,對照!A:C,2,0),"") -> 顏豪志 | AF18: =IFERROR(VLOOKUP(J18&K18,對照!A:C,3,0),"") -> 高屏營銷處
C19: TT00 | D19: 10 | E19: OM | F19: TW019173A1 | G19: 樂嘉家電 | H19: TWSG003199 | I19: 樂嘉家電(輜汽倉) | J19: TT230597 | K19: 顏 豪志 | L19: A | M19: Active | N19: 11007247 | O19: Dealer Sales_KaoPing Team | P19: SAL | R19: SALES | S19: 45909 | T19: 401769 | U19: 11000151 | V19: LGETT | W19: false | X19: changsun.yang_chang sun Yang | Y19: 46203 | Z19: 0.80075231 | AA19: changsun.yang_chang sun Yang | AB19: 46203 | AC19: 0.80075231 | AE19: =IFERROR(VLOOKUP(J19&K19,對照!A:C,2,0),"") -> 顏豪志 | AF19: =IFERROR(VLOOKUP(J19&K19,對照!A:C,3,0),"") -> 高屏營銷處
C20: TT00 | D20: 10 | E20: OM | F20: TW019173A1 | G20: 樂嘉家電 | H20: TWSG003200 | I20: 樂嘉家電(東源倉) | J20: TT230597 | K20: 顏 豪志 | L20: A | M20: Active | N20: 11007247 | O20: Dealer Sales_KaoPing Team | P20: SAL | R20: SALES | S20: 45909 | T20: 401769 | U20: 11000151 | V20: LGETT | W20: false | X20: changsun.yang_chang sun Yang | Y20: 46203 | Z20: 0.80075231 | AA20: changsun.yang_chang sun Yang | AB20: 46203 | AC20: 0.80075231 | AE20: =IFERROR(VLOOKUP(J20&K20,對照!A:C,2,0),"") -> 顏豪志 | AF20: =IFERROR(VLOOKUP(J20&K20,對照!A:C,3,0),"") -> 高屏營銷處
C21: TT00 | D21: 10 | E21: OM | F21: TW019173A1 | G21: 樂嘉家電 | H21: TWSG003201 | I21: 樂嘉家電(三多門市) | J21: TT230597 | K21: 顏 豪志 | L21: A | M21: Active | N21: 11007247 | O21: Dealer Sales_KaoPing Team | P21: SAL | R21: SALES | S21: 45909 | T21: 401769 | U21: 11000151 | V21: LGETT | W21: false | X21: changsun.yang_chang sun Yang | Y21: 46203 | Z21: 0.80075231 | AA21: changsun.yang_chang sun Yang | AB21: 46203 | AC21: 0.80075231 | AE21: =IFERROR(VLOOKUP(J21&K21,對照!A:C,2,0),"") -> 顏豪志 | AF21: =IFERROR(VLOOKUP(J21&K21,對照!A:C,3,0),"") -> 高屏營銷處
C22: TT00 | D22: 10 | E22: OM | F22: TW019173A1 | G22: 樂嘉家電 | J22: TT230597 | K22: 顏 豪志 | L22: A | M22: Active | N22: 11007247 | O22: Dealer Sales_KaoPing Team | P22: SAL | R22: SALES | S22: 45904 | T22: 401769 | U22: 11000151 | V22: LGETT | W22: false | X22: changsun.yang_chang sun Yang | Y22: 46203 | Z22: 0.80075231 | AA22: changsun.yang_chang sun Yang | AB22: 46203 | AC22: 0.80075231 | AE22: =IFERROR(VLOOKUP(J22&K22,對照!A:C,2,0),"") -> 顏豪志 | AF22: =IFERROR(VLOOKUP(J22&K22,對照!A:C,3,0),"") -> 高屏營銷處
C23: TT00 | D23: 10 | E23: OM | F23: TW019173A1 | G23: 樂嘉家電 | H23: TWSG003196 | I23: 樂嘉家電有限公司 | J23: TT230597 | K23: 顏 豪志 | L23: A | M23: Active | N23: 11007247 | O23: Dealer Sales_KaoPing Team | P23: SAL | R23: SALES | S23: 45904 | T23: 401769 | U23: 11000151 | V23: LGETT | W23: false | X23: changsun.yang_chang sun Yang | Y23: 46203 | Z23: 0.80075231 | AA23: changsun.yang_chang sun Yang | AB23: 46203 | AC23: 0.80075231 | AE23: =IFERROR(VLOOKUP(J23&K23,對照!A:C,2,0),"") -> 顏豪志 | AF23: =IFERROR(VLOOKUP(J23&K23,對照!A:C,3,0),"") -> 高屏營銷處
C24: TT00 | D24: 10 | E24: OM | F24: TW018614A1 | G24: 鴻昇興業行 | J24: TT230597 | K24: 顏 豪志 | L24: A | M24: Active | N24: 11007247 | O24: Dealer Sales_KaoPing Team | P24: SAL | R24: SALES | S24: 45775 | T24: 401769 | U24: 11000151 | V24: LGETT | W24: false | X24: changsun.yang_chang sun Yang | Y24: 46203 | Z24: 0.80075231 | AA24: changsun.yang_chang sun Yang | AB24: 46203 | AC24: 0.80075231 | AE24: =IFERROR(VLOOKUP(J24&K24,對照!A:C,2,0),"") -> 顏豪志 | AF24: =IFERROR(VLOOKUP(J24&K24,對照!A:C,3,0),"") -> 高屏營銷處
C25: TT00 | D25: 10 | E25: OM | F25: TW219426A1 | G25: 章記企業有限公司 | H25: TWSG002365 | I25: 章記(橋頭倉) | J25: TT230597 | K25: 顏 豪志 | L25: A | M25: Active | N25: 11007247 | O25: Dealer Sales_KaoPing Team | P25: SAL | R25: SALES | S25: 45771 | T25: 401769 | U25: 11000151 | V25: LGETT | W25: false | X25: changsun.yang_chang sun Yang | Y25: 46203 | Z25: 0.80075231 | AA25: changsun.yang_chang sun Yang | AB25: 46203 | AC25: 0.80075231 | AE25: =IFERROR(VLOOKUP(J25&K25,對照!A:C,2,0),"") -> 顏豪志 | AF25: =IFERROR(VLOOKUP(J25&K25,對照!A:C,3,0),"") -> 高屏營銷處
C26: TT00 | D26: 10 | E26: OM | F26: TW219578A1 | G26: 培芝家電快速服務中心 | H26: TWSG002665 | I26: 培芝家電(三多門市) | J26: TT230597 | K26: 顏 豪志 | L26: A | M26: Active | N26: 11007247 | O26: Dealer Sales_KaoPing Team | P26: SAL | R26: SALES | S26: 45712 | T26: 401769 | U26: 11000151 | V26: LGETT | W26: false | X26: changsun.yang_chang sun Yang | Y26: 46203 | Z26: 0.80075231 | AA26: changsun.yang_chang sun Yang | AB26: 46203 | AC26: 0.80075231 | AE26: =IFERROR(VLOOKUP(J26&K26,對照!A:C,2,0),"") -> 顏豪志 | AF26: =IFERROR(VLOOKUP(J26&K26,對照!A:C,3,0),"") -> 高屏營銷處
C27: TT00 | D27: 10 | E27: OM | F27: TW219578A1 | G27: 培芝家電快速服務中心 | H27: TWSG002664 | I27: 培芝家電(東源倉庫) | J27: TT230597 | K27: 顏 豪志 | L27: A | M27: Active | N27: 11007247 | O27: Dealer Sales_KaoPing Team | P27: SAL | R27: SALES | S27: 45712 | T27: 401769 | U27: 11000151 | V27: LGETT | W27: false | X27: changsun.yang_chang sun Yang | Y27: 46203 | Z27: 0.80075231 | AA27: changsun.yang_chang sun Yang | AB27: 46203 | AC27: 0.80075231 | AE27: =IFERROR(VLOOKUP(J27&K27,對照!A:C,2,0),"") -> 顏豪志 | AF27: =IFERROR(VLOOKUP(J27&K27,對照!A:C,3,0),"") -> 高屏營銷處
C28: TT00 | D28: 10 | E28: OM | F28: TW219578A1 | G28: 培芝家電快速服務中心 | H28: TWSG002663 | I28: 培芝家電(輜汽倉庫) | J28: TT230597 | K28: 顏 豪志 | L28: A | M28: Active | N28: 11007247 | O28: Dealer Sales_KaoPing Team | P28: SAL | R28: SALES | S28: 45712 | T28: 401769 | U28: 11000151 | V28: LGETT | W28: false | X28: changsun.yang_chang sun Yang | Y28: 46203 | Z28: 0.80075231 | AA28: changsun.yang_chang sun Yang | AB28: 46203 | AC28: 0.80075231 | AE28: =IFERROR(VLOOKUP(J28&K28,對照!A:C,2,0),"") -> 顏豪志 | AF28: =IFERROR(VLOOKUP(J28&K28,對照!A:C,3,0),"") -> 高屏營銷處
C29: TT00 | D29: 10 | E29: OM | F29: TW219578A1 | G29: 培芝家電快速服務中心 | H29: TWSG002666 | I29: 培芝家電快速服務中心 | J29: TT230597 | K29: 顏 豪志 | L29: A | M29: Active | N29: 11007247 | O29: Dealer Sales_KaoPing Team | P29: SAL | R29: SALES | S29: 45681 | T29: 401769 | U29: 11000151 | V29: LGETT | W29: false | X29: changsun.yang_chang sun Yang | Y29: 46203 | Z29: 0.80075231 | AA29: changsun.yang_chang sun Yang | AB29: 46203 | AC29: 0.80075231 | AE29: =IFERROR(VLOOKUP(J29&K29,對照!A:C,2,0),"") -> 顏豪志 | AF29: =IFERROR(VLOOKUP(J29&K29,對照!A:C,3,0),"") -> 高屏營銷處
C30: TT00 | D30: 10 | E30: OM | F30: TW219578A1 | G30: 培芝家電快速服務中心 | J30: TT230597 | K30: 顏 豪志 | L30: A | M30: Active | N30: 11007247 | O30: Dealer Sales_KaoPing Team | P30: SAL | R30: SALES | S30: 45681 | T30: 401769 | U30: 11000151 | V30: LGETT | W30: false | X30: changsun.yang_chang sun Yang | Y30: 46203 | Z30: 0.80075231 | AA30: changsun.yang_chang sun Yang | AB30: 46203 | AC30: 0.80075231 | AE30: =IFERROR(VLOOKUP(J30&K30,對照!A:C,2,0),"") -> 顏豪志 | AF30: =IFERROR(VLOOKUP(J30&K30,對照!A:C,3,0),"") -> 高屏營銷處
C31: TT00 | D31: 10 | E31: OM | F31: TW018773A1 | G31: 集盛股份有限公司 | H31: TWSG000200 | I31: 集盛(股)公司(彰化) | J31: TT230597 | K31: 顏 豪志 | L31: A | M31: Active | N31: 11007247 | O31: Dealer Sales_KaoPing Team | P31: SAL | R31: SALES | S31: 45642 | T31: 401769 | U31: 11000151 | V31: LGETT | W31: false | X31: changsun.yang_chang sun Yang | Y31: 46203 | Z31: 0.80075231 | AA31: changsun.yang_chang sun Yang | AB31: 46203 | AC31: 0.80075231 | AE31: =IFERROR(VLOOKUP(J31&K31,對照!A:C,2,0),"") -> 顏豪志 | AF31: =IFERROR(VLOOKUP(J31&K31,對照!A:C,3,0),"") -> 高屏營銷處
C32: TT00 | D32: 10 | E32: OM | F32: TW018773A1 | G32: 集盛股份有限公司 | H32: TWSG003070 | I32: 集盛(股)公司(台中烏日) | J32: TT230597 | K32: 顏 豪志 | L32: A | M32: Active | N32: 11007247 | O32: Dealer Sales_KaoPing Team | P32: SAL | R32: SALES | S32: 45579 | T32: 401769 | U32: 11000151 | V32: LGETT | W32: false | X32: changsun.yang_chang sun Yang | Y32: 46203 | Z32: 0.80075231 | AA32: changsun.yang_chang sun Yang | AB32: 46203 | AC32: 0.80075231 | AE32: =IFERROR(VLOOKUP(J32&K32,對照!A:C,2,0),"") -> 顏豪志 | AF32: =IFERROR(VLOOKUP(J32&K32,對照!A:C,3,0),"") -> 高屏營銷處
C33: TT00 | D33: 10 | E33: OM | F33: TW018773A1 | G33: 集盛股份有限公司 | H33: TWSG003069 | I33: 集盛(股)公司(桃園) | J33: TT230597 | K33: 顏 豪志 | L33: A | M33: Active | N33: 11007247 | O33: Dealer Sales_KaoPing Team | P33: SAL | R33: SALES | S33: 45579 | T33: 401769 | U33: 11000151 | V33: LGETT | W33: false | X33: changsun.yang_chang sun Yang | Y33: 46203 | Z33: 0.80075231 | AA33: changsun.yang_chang sun Yang | AB33: 46203 | AC33: 0.80075231 | AE33: =IFERROR(VLOOKUP(J33&K33,對照!A:C,2,0),"") -> 顏豪志 | AF33: =IFERROR(VLOOKUP(J33&K33,對照!A:C,3,0),"") -> 高屏營銷處
C34: TT00 | D34: 10 | E34: OM | F34: TW219468A1 | G34: 賽門音響企業社 | J34: TT230597 | K34: 顏 豪志 | L34: A | M34: Active | N34: 11007247 | O34: Dealer Sales_KaoPing Team | P34: SAL | R34: SALES | S34: 45215 | T34: 401769 | U34: 11000151 | V34: LGETT | W34: false | X34: changsun.yang_chang sun Yang | Y34: 46203 | Z34: 0.80075231 | AA34: changsun.yang_chang sun Yang | AB34: 46203 | AC34: 0.80075231 | AE34: =IFERROR(VLOOKUP(J34&K34,對照!A:C,2,0),"") -> 顏豪志 | AF34: =IFERROR(VLOOKUP(J34&K34,對照!A:C,3,0),"") -> 高屏營銷處
C35: TT00 | D35: 10 | E35: OM | F35: TW219426A1 | G35: 章記企業有限公司 | J35: TT230597 | K35: 顏 豪志 | L35: A | M35: Active | N35: 11007247 | O35: Dealer Sales_KaoPing Team | P35: SAL | R35: SALES | S35: 45108 | T35: 401769 | U35: 11000151 | V35: LGETT | W35: false | X35: changsun.yang_chang sun Yang | Y35: 46203 | Z35: 0.80075231 | AA35: changsun.yang_chang sun Yang | AB35: 46203 | AC35: 0.80075231 | AE35: =IFERROR(VLOOKUP(J35&K35,對照!A:C,2,0),"") -> 顏豪志 | AF35: =IFERROR(VLOOKUP(J35&K35,對照!A:C,3,0),"") -> 高屏營銷處
C36: TT00 | D36: 10 | E36: OM | F36: TW219337A1 | G36: 睿凡企業 | J36: TT230597 | K36: 顏 豪志 | L36: A | M36: Active | N36: 11007247 | O36: Dealer Sales_KaoPing Team | P36: SAL | R36: SALES | S36: 44259 | T36: 401769 | U36: 11000151 | V36: LGETT | W36: false | X36: changsun.yang_chang sun Yang | Y36: 46203 | Z36: 0.80075231 | AA36: changsun.yang_chang sun Yang | AB36: 46203 | AC36: 0.80075231 | AE36: =IFERROR(VLOOKUP(J36&K36,對照!A:C,2,0),"") -> 顏豪志 | AF36: =IFERROR(VLOOKUP(J36&K36,對照!A:C,3,0),"") -> 高屏營銷處
C37: TT00 | D37: 10 | E37: OM | F37: TW016815A1 | G37: 萊旺電器行 | J37: TT230597 | K37: 顏 豪志 | L37: A | M37: Active | N37: 11007247 | O37: Dealer Sales_KaoPing Team | P37: SAL | R37: SALES | S37: 44062 | T37: 401769 | U37: 11000151 | V37: LGETT | W37: false | X37: changsun.yang_chang sun Yang | Y37: 46203 | Z37: 0.80075231 | AA37: changsun.yang_chang sun Yang | AB37: 46203 | AC37: 0.80075231 | AE37: =IFERROR(VLOOKUP(J37&K37,對照!A:C,2,0),"") -> 顏豪志 | AF37: =IFERROR(VLOOKUP(J37&K37,對照!A:C,3,0),"") -> 高屏營銷處
C38: TT00 | D38: 10 | E38: OM | F38: TW018773A1 | G38: 集盛股份有限公司 | J38: TT230597 | K38: 顏 豪志 | L38: A | M38: Active | N38: 11007247 | O38: Dealer Sales_KaoPing Team | P38: SAL | R38: SALES | S38: 44054 | T38: 401769 | U38: 11000151 | V38: LGETT | W38: false | X38: changsun.yang_chang sun Yang | Y38: 46203 | Z38: 0.80075231 | AA38: changsun.yang_chang sun Yang | AB38: 46203 | AC38: 0.80075231 | AE38: =IFERROR(VLOOKUP(J38&K38,對照!A:C,2,0),"") -> 顏豪志 | AF38: =IFERROR(VLOOKUP(J38&K38,對照!A:C,3,0),"") -> 高屏營銷處
C39: TT00 | D39: 10 | E39: OM | F39: TW219307A1 | G39: 杉泰電器 | J39: TT230597 | K39: 顏 豪志 | L39: A | M39: Active | N39: 11007247 | O39: Dealer Sales_KaoPing Team | P39: SAL | R39: SALES | S39: 43908 | T39: 401769 | U39: 11000151 | V39: LGETT | W39: false | X39: changsun.yang_chang sun Yang | Y39: 46203 | Z39: 0.80075231 | AA39: changsun.yang_chang sun Yang | AB39: 46203 | AC39: 0.80075231 | AE39: =IFERROR(VLOOKUP(J39&K39,對照!A:C,2,0),"") -> 顏豪志 | AF39: =IFERROR(VLOOKUP(J39&K39,對照!A:C,3,0),"") -> 高屏營銷處
C40: TT00 | D40: 10 | E40: OM | F40: TW010987A1 | G40: 聯立貿易有限公司 | J40: TT230597 | K40: 顏 豪志 | L40: A | M40: Active | N40: 11007247 | O40: Dealer Sales_KaoPing Team | P40: SAL | R40: SALES | S40: 43691 | T40: 401769 | U40: 11000151 | V40: LGETT | W40: false | X40: changsun.yang_chang sun Yang | Y40: 46203 | Z40: 0.80075231 | AA40: changsun.yang_chang sun Yang | AB40: 46203 | AC40: 0.80075231 | AE40: =IFERROR(VLOOKUP(J40&K40,對照!A:C,2,0),"") -> 顏豪志 | AF40: =IFERROR(VLOOKUP(J40&K40,對照!A:C,3,0),"") -> 高屏營銷處
C41: TT00 | D41: 10 | E41: OM | F41: TW010987A1 | G41: 聯立貿易有限公司 | H41: TW010987 | I41: 聯立貿易有限公司 | J41: TT230597 | K41: 顏 豪志 | L41: A | M41: Active | N41: 11007247 | O41: Dealer Sales_KaoPing Team | P41: SAL | R41: SALES | S41: 43691 | T41: 401769 | U41: 11000151 | V41: LGETT | W41: false | X41: changsun.yang_chang sun Yang | Y41: 46203 | Z41: 0.80075231 | AA41: changsun.yang_chang sun Yang | AB41: 46203 | AC41: 0.80075231 | AE41: =IFERROR(VLOOKUP(J41&K41,對照!A:C,2,0),"") -> 顏豪志 | AF41: =IFERROR(VLOOKUP(J41&K41,對照!A:C,3,0),"") -> 高屏營銷處
C42: TT00 | D42: 10 | E42: OM | F42: TW011007A1 | G42: 慶旺電器 | J42: TT230597 | K42: 顏 豪志 | L42: A | M42: Active | N42: 11007247 | O42: Dealer Sales_KaoPing Team | P42: SAL | R42: SALES | S42: 43691 | T42: 401769 | U42: 11000151 | V42: LGETT | W42: false | X42: changsun.yang_chang sun Yang | Y42: 46203 | Z42: 0.80075231 | AA42: changsun.yang_chang sun Yang | AB42: 46203 | AC42: 0.80075231 | AE42: =IFERROR(VLOOKUP(J42&K42,對照!A:C,2,0),"") -> 顏豪志 | AF42: =IFERROR(VLOOKUP(J42&K42,對照!A:C,3,0),"") -> 高屏營銷處
C43: TT00 | D43: 10 | E43: OM | F43: TW011398A1 | G43: 勁鋒電器 | H43: TW011398 | I43: 勁鋒電器行 | J43: TT230597 | K43: 顏 豪志 | L43: A | M43: Active | N43: 11007247 | O43: Dealer Sales_KaoPing Team | P43: SAL | R43: SALES | S43: 43691 | T43: 401769 | U43: 11000151 | V43: LGETT | W43: false | X43: changsun.yang_chang sun Yang | Y43: 46203 | Z43: 0.80075231 | AA43: changsun.yang_chang sun Yang | AB43: 46203 | AC43: 0.80075231 | AE43: =IFERROR(VLOOKUP(J43&K43,對照!A:C,2,0),"") -> 顏豪志 | AF43: =IFERROR(VLOOKUP(J43&K43,對照!A:C,3,0),"") -> 高屏營銷處
C44: TT00 | D44: 10 | E44: OM | F44: TW012526A1 | G44: 萊旺企業 | H44: TWSG001735 | I44: 萊旺企業 | J44: TT230597 | K44: 顏 豪志 | L44: A | M44: Active | N44: 11007247 | O44: Dealer Sales_KaoPing Team | P44: SAL | R44: SALES | S44: 43691 | T44: 401769 | U44: 11000151 | V44: LGETT | W44: false | X44: changsun.yang_chang sun Yang | Y44: 46203 | Z44: 0.80075231 | AA44: changsun.yang_chang sun Yang | AB44: 46203 | AC44: 0.80075231 | AE44: =IFERROR(VLOOKUP(J44&K44,對照!A:C,2,0),"") -> 顏豪志 | AF44: =IFERROR(VLOOKUP(J44&K44,對照!A:C,3,0),"") -> 高屏營銷處
C45: TT00 | D45: 10 | E45: OM | F45: TW012526A1 | G45: 萊旺企業 | H45: TW012526 | I45: 萊旺企業有限公司 | J45: TT230597 | K45: 顏 豪志 | L45: A | M45: Active | N45: 11007247 | O45: Dealer Sales_KaoPing Team | P45: SAL | R45: SALES | S45: 43691 | T45: 401769 | U45: 11000151 | V45: LGETT | W45: false | X45: changsun.yang_chang sun Yang | Y45: 46203 | Z45: 0.80075231 | AA45: changsun.yang_chang sun Yang | AB45: 46203 | AC45: 0.80075231 | AE45: =IFERROR(VLOOKUP(J45&K45,對照!A:C,2,0),"") -> 顏豪志 | AF45: =IFERROR(VLOOKUP(J45&K45,對照!A:C,3,0),"") -> 高屏營銷處
C46: TT00 | D46: 10 | E46: OM | F46: TW012526A1 | G46: 萊旺企業 | J46: TT230597 | K46: 顏 豪志 | L46: A | M46: Active | N46: 11007247 | O46: Dealer Sales_KaoPing Team | P46: SAL | R46: SALES | S46: 43691 | T46: 401769 | U46: 11000151 | V46: LGETT | W46: false | X46: changsun.yang_chang sun Yang | Y46: 46203 | Z46: 0.80075231 | AA46: changsun.yang_chang sun Yang | AB46: 46203 | AC46: 0.80075231 | AE46: =IFERROR(VLOOKUP(J46&K46,對照!A:C,2,0),"") -> 顏豪志 | AF46: =IFERROR(VLOOKUP(J46&K46,對照!A:C,3,0),"") -> 高屏營銷處
C47: TT00 | D47: 10 | E47: OM | F47: TW014331A1 | G47: 上眾電器 | H47: TW014331 | I47: 上眾電器有限公司 | J47: TT230597 | K47: 顏 豪志 | L47: A | M47: Active | N47: 11007247 | O47: Dealer Sales_KaoPing Team | P47: SAL | R47: SALES | S47: 43691 | T47: 401769 | U47: 11000151 | V47: LGETT | W47: false | X47: changsun.yang_chang sun Yang | Y47: 46203 | Z47: 0.80075231 | AA47: changsun.yang_chang sun Yang | AB47: 46203 | AC47: 0.80075231 | AE47: =IFERROR(VLOOKUP(J47&K47,對照!A:C,2,0),"") -> 顏豪志 | AF47: =IFERROR(VLOOKUP(J47&K47,對照!A:C,3,0),"") -> 高屏營銷處
C48: TT00 | D48: 10 | E48: OM | F48: TW016815A1 | G48: 萊旺電器行 | H48: TWSG001957 | I48: 萊旺(山腳倉庫) | J48: TT230597 | K48: 顏 豪志 | L48: A | M48: Active | N48: 11007247 | O48: Dealer Sales_KaoPing Team | P48: SAL | R48: SALES | S48: 43691 | T48: 401769 | U48: 11000151 | V48: LGETT | W48: false | X48: changsun.yang_chang sun Yang | Y48: 46203 | Z48: 0.80075231 | AA48: changsun.yang_chang sun Yang | AB48: 46203 | AC48: 0.80075231 | AE48: =IFERROR(VLOOKUP(J48&K48,對照!A:C,2,0),"") -> 顏豪志 | AF48: =IFERROR(VLOOKUP(J48&K48,對照!A:C,3,0),"") -> 高屏營銷處
C49: TT00 | D49: 10 | E49: OM | F49: TW016815A1 | G49: 萊旺電器行 | H49: TWSG001959 | I49: 萊旺電器行 | J49: TT230597 | K49: 顏 豪志 | L49: A | M49: Active | N49: 11007247 | O49: Dealer Sales_KaoPing Team | P49: SAL | R49: SALES | S49: 43691 | T49: 401769 | U49: 11000151 | V49: LGETT | W49: false | X49: changsun.yang_chang sun Yang | Y49: 46203 | Z49: 0.80075231 | AA49: changsun.yang_chang sun Yang | AB49: 46203 | AC49: 0.80075231 | AE49: =IFERROR(VLOOKUP(J49&K49,對照!A:C,2,0),"") -> 顏豪志 | AF49: =IFERROR(VLOOKUP(J49&K49,對照!A:C,3,0),"") -> 高屏營銷處
C50: TT00 | D50: 10 | E50: OM | F50: TW016815A1 | G50: 萊旺電器行 | H50: TWSG002744 | I50: 萊旺電器行 | J50: TT230597 | K50: 顏 豪志 | L50: A | M50: Active | N50: 11007247 | O50: Dealer Sales_KaoPing Team | P50: SAL | R50: SALES | S50: 43691 | T50: 401769 | U50: 11000151 | V50: LGETT | W50: false | X50: changsun.yang_chang sun Yang | Y50: 46203 | Z50: 0.80075231 | AA50: changsun.yang_chang sun Yang | AB50: 46203 | AC50: 0.80075231 | AE50: =IFERROR(VLOOKUP(J50&K50,對照!A:C,2,0),"") -> 顏豪志 | AF50: =IFERROR(VLOOKUP(J50&K50,對照!A:C,3,0),"") -> 高屏營銷處
C51: TT00 | D51: 10 | E51: OM | F51: TW017338A1 | G51: 首豐企業社 | J51: TT230597 | K51: 顏 豪志 | L51: A | M51: Active | N51: 11007247 | O51: Dealer Sales_KaoPing Team | P51: SAL | R51: SALES | S51: 43691 | T51: 401769 | U51: 11000151 | V51: LGETT | W51: false | X51: changsun.yang_chang sun Yang | Y51: 46203 | Z51: 0.80075231 | AA51: changsun.yang_chang sun Yang | AB51: 46203 | AC51: 0.80075231 | AE51: =IFERROR(VLOOKUP(J51&K51,對照!A:C,2,0),"") -> 顏豪志 | AF51: =IFERROR(VLOOKUP(J51&K51,對照!A:C,3,0),"") -> 高屏營銷處
C52: TT00 | D52: 10 | E52: OM | F52: TW018285A1 | G52: 永漢允有限公司 | H52: TWSG002648 | I52: 永漢允有限公司 | J52: TT230597 | K52: 顏 豪志 | L52: A | M52: Active | N52: 11007247 | O52: Dealer Sales_KaoPing Team | P52: SAL | R52: SALES | S52: 43691 | T52: 401769 | U52: 11000151 | V52: LGETT | W52: false | X52: changsun.yang_chang sun Yang | Y52: 46203 | Z52: 0.80075231 | AA52: changsun.yang_chang sun Yang | AB52: 46203 | AC52: 0.80075231 | AE52: =IFERROR(VLOOKUP(J52&K52,對照!A:C,2,0),"") -> 顏豪志 | AF52: =IFERROR(VLOOKUP(J52&K52,對照!A:C,3,0),"") -> 高屏營銷處
C53: TT00 | D53: 10 | E53: OM | F53: TW018290A1 | G53: 富豪音響影視企業社 | J53: TT230597 | K53: 顏 豪志 | L53: A | M53: Active | N53: 11007247 | O53: Dealer Sales_KaoPing Team | P53: SAL | R53: SALES | S53: 43691 | T53: 401769 | U53: 11000151 | V53: LGETT | W53: false | X53: changsun.yang_chang sun Yang | Y53: 46203 | Z53: 0.80075231 | AA53: changsun.yang_chang sun Yang | AB53: 46203 | AC53: 0.80075231 | AE53: =IFERROR(VLOOKUP(J53&K53,對照!A:C,2,0),"") -> 顏豪志 | AF53: =IFERROR(VLOOKUP(J53&K53,對照!A:C,3,0),"") -> 高屏營銷處
C54: TT00 | D54: 10 | E54: OM | F54: TW010987A1 | G54: 聯立貿易有限公司 | J54: TT230597 | K54: 顏 豪志 | L54: A | M54: Active | N54: 11007247 | O54: Dealer Sales_KaoPing Team | P54: SAL | R54: SALES | S54: 43690 | T54: 401769 | U54: 11000151 | V54: LGETT | W54: false | X54: changsun.yang_chang sun Yang | Y54: 46203 | Z54: 0.80075231 | AA54: changsun.yang_chang sun Yang | AB54: 46203 | AC54: 0.80075231 | AE54: =IFERROR(VLOOKUP(J54&K54,對照!A:C,2,0),"") -> 顏豪志 | AF54: =IFERROR(VLOOKUP(J54&K54,對照!A:C,3,0),"") -> 高屏營銷處
C55: TT00 | D55: 10 | E55: OM | F55: TW010987A1 | G55: 聯立貿易有限公司 | H55: TW010987 | I55: 聯立貿易有限公司 | J55: TT230597 | K55: 顏 豪志 | L55: A | M55: Active | N55: 11007247 | O55: Dealer Sales_KaoPing Team | P55: SAL | R55: SALES | S55: 43690 | T55: 401769 | U55: 11000151 | V55: LGETT | W55: false | X55: changsun.yang_chang sun Yang | Y55: 46203 | Z55: 0.80075231 | AA55: changsun.yang_chang sun Yang | AB55: 46203 | AC55: 0.80075231 | AE55: =IFERROR(VLOOKUP(J55&K55,對照!A:C,2,0),"") -> 顏豪志 | AF55: =IFERROR(VLOOKUP(J55&K55,對照!A:C,3,0),"") -> 高屏營銷處
C56: TT00 | D56: 10 | E56: OM | F56: TW016379A1 | G56: 上晟國際 | H56: TWSG001032 | I56: 上晟(汀洲店) | J56: TT229825 | K56: 錢 亮均 | L56: A | M56: Active | N56: 11007249 | O56: Dealer Sales_Taipei Team | P56: SAL | R56: SALES | S56: 46600 | T56: 401769 | U56: 11000151 | V56: LGETT | W56: false | X56: changsun.yang_chang sun Yang | Y56: 46203 | Z56: 0.80075231 | AA56: yuchuan.hsiao_Yuchuan Hsiao | AB56: 46252 | AC56: 0.38884259 | AE56: =IFERROR(VLOOKUP(J56&K56,對照!A:C,2,0),"") -> 錢亮均 | AF56: =IFERROR(VLOOKUP(J56&K56,對照!A:C,3,0),"") -> 台北營銷處
C57: TT00 | D57: 10 | E57: OM | F57: TW016379A1 | G57: 上晟國際 | H57: TWSG000904 | I57: 上晟(映像) | J57: TT229825 | K57: 錢 亮均 | L57: A | M57: Active | N57: 11007249 | O57: Dealer Sales_Taipei Team | P57: SAL | R57: SALES | S57: 46600 | T57: 401769 | U57: 11000151 | V57: LGETT | W57: false | X57: changsun.yang_chang sun Yang | Y57: 46203 | Z57: 0.80075231 | AA57: yuchuan.hsiao_Yuchuan Hsiao | AB57: 46252 | AC57: 0.38884259 | AE57: =IFERROR(VLOOKUP(J57&K57,對照!A:C,2,0),"") -> 錢亮均 | AF57: =IFERROR(VLOOKUP(J57&K57,對照!A:C,3,0),"") -> 台北營銷處
C58: TT00 | D58: 10 | E58: OM | F58: TW016379A1 | G58: 上晟國際 | H58: TWSG000905 | I58: 上晟(三重店) | J58: TT229825 | K58: 錢 亮均 | L58: A | M58: Active | N58: 11007249 | O58: Dealer Sales_Taipei Team | P58: SAL | R58: SALES | S58: 46600 | T58: 401769 | U58: 11000151 | V58: LGETT | W58: false | X58: changsun.yang_chang sun Yang | Y58: 46203 | Z58: 0.80075231 | AA58: yuchuan.hsiao_Yuchuan Hsiao | AB58: 46252 | AC58: 0.38884259 | AE58: =IFERROR(VLOOKUP(J58&K58,對照!A:C,2,0),"") -> 錢亮均 | AF58: =IFERROR(VLOOKUP(J58&K58,對照!A:C,3,0),"") -> 台北營銷處
C59: TT00 | D59: 10 | E59: OM | F59: TW010435A1 | G59: 上順電器 | J59: TT229825 | K59: 錢 亮均 | L59: A | M59: Active | N59: 11007249 | O59: Dealer Sales_Taipei Team | P59: SAL | R59: SALES | S59: 46240 | T59: 401769 | U59: 11000151 | V59: LGETT | W59: false | X59: changsun.yang_chang sun Yang | Y59: 46203 | Z59: 0.80075231 | AA59: chiajung.wu_Chiajung Wu | AB59: 46240 | AC59: 0.57846065 | AE59: =IFERROR(VLOOKUP(J59&K59,對照!A:C,2,0),"") -> 錢亮均 | AF59: =IFERROR(VLOOKUP(J59&K59,對照!A:C,3,0),"") -> 台北營銷處
C60: TT00 | D60: 10 | E60: OM | F60: TW010437A1 | G60: 今漢 | J60: TT229825 | K60: 錢 亮均 | L60: A | M60: Active | N60: 11007249 | O60: Dealer Sales_Taipei Team | P60: SAL | R60: SALES | S60: 46240 | T60: 401769 | U60: 11000151 | V60: LGETT | W60: false | X60: changsun.yang_chang sun Yang | Y60: 46203 | Z60: 0.80075231 | AA60: chiajung.wu_Chiajung Wu | AB60: 46240 | AC60: 0.58083333 | AE60: =IFERROR(VLOOKUP(J60&K60,對照!A:C,2,0),"") -> 錢亮均 | AF60: =IFERROR(VLOOKUP(J60&K60,對照!A:C,3,0),"") -> 台北營銷處
C61: TT00 | D61: 10 | E61: OM | F61: TW010662A1 | G61: 老雙億實業 | J61: TT229825 | K61: 錢 亮均 | L61: A | M61: Active | N61: 11007249 | O61: Dealer Sales_Taipei Team | P61: SAL | R61: SALES | S61: 46240 | T61: 401769 | U61: 11000151 | V61: LGETT | W61: false | X61: changsun.yang_chang sun Yang | Y61: 46203 | Z61: 0.80075231 | AA61: chiajung.wu_Chiajung Wu | AB61: 46240 | AC61: 0.58201389 | AE61: =IFERROR(VLOOKUP(J61&K61,對照!A:C,2,0),"") -> 錢亮均 | AF61: =IFERROR(VLOOKUP(J61&K61,對照!A:C,3,0),"") -> 台北營銷處
C62: TT00 | D62: 10 | E62: OM | F62: TW010689A1 | G62: 弘象電器 | H62: TW010689 | I62: 弘象電器有限公司 | J62: TT229825 | K62: 錢 亮均 | L62: A | M62: Active | N62: 11007249 | O62: Dealer Sales_Taipei Team | P62: SAL | R62: SALES | S62: 46240 | T62: 401769 | U62: 11000151 | V62: LGETT | W62: false | X62: changsun.yang_chang sun Yang | Y62: 46203 | Z62: 0.80075231 | AA62: chiajung.wu_Chiajung Wu | AB62: 46240 | AC62: 0.58143519 | AE62: =IFERROR(VLOOKUP(J62&K62,對照!A:C,2,0),"") -> 錢亮均 | AF62: =IFERROR(VLOOKUP(J62&K62,對照!A:C,3,0),"") -> 台北營銷處
C63: TT00 | D63: 10 | E63: OM | F63: TW010836A1 | G63: 宏仁電器 | J63: TT229825 | K63: 錢 亮均 | L63: A | M63: Active | N63: 11007249 | O63: Dealer Sales_Taipei Team | P63: SAL | R63: SALES | S63: 46240 | T63: 401769 | U63: 11000151 | V63: LGETT | W63: false | X63: changsun.yang_chang sun Yang | Y63: 46203 | Z63: 0.80075231 | AA63: chiajung.wu_Chiajung Wu | AB63: 46240 | AC63: 0.57746528 | AE63: =IFERROR(VLOOKUP(J63&K63,對照!A:C,2,0),"") -> 錢亮均 | AF63: =IFERROR(VLOOKUP(J63&K63,對照!A:C,3,0),"") -> 台北營銷處
C64: TT00 | D64: 10 | E64: OM | F64: TW011666A1 | G64: 鴻輝電器 | J64: TT229825 | K64: 錢 亮均 | L64: A | M64: Active | N64: 11007249 | O64: Dealer Sales_Taipei Team | P64: SAL | R64: SALES | S64: 46240 | T64: 401769 | U64: 11000151 | V64: LGETT | W64: false | X64: changsun.yang_chang sun Yang | Y64: 46203 | Z64: 0.80075231 | AA64: chiajung.wu_Chiajung Wu | AB64: 46240 | AC64: 0.58396991 | AE64: =IFERROR(VLOOKUP(J64&K64,對照!A:C,2,0),"") -> 錢亮均 | AF64: =IFERROR(VLOOKUP(J64&K64,對照!A:C,3,0),"") -> 台北營銷處
C65: TT00 | D65: 10 | E65: OM | F65: TW013714A1 | G65: 聯錩順電器 | J65: TT229825 | K65: 錢 亮均 | L65: A | M65: Active | N65: 11007249 | O65: Dealer Sales_Taipei Team | P65: SAL | R65: SALES | S65: 46240 | T65: 401769 | U65: 11000151 | V65: LGETT | W65: false | X65: changsun.yang_chang sun Yang | Y65: 46203 | Z65: 0.80075231 | AA65: chiajung.wu_Chiajung Wu | AB65: 46240 | AC65: 0.62043981 | AE65: =IFERROR(VLOOKUP(J65&K65,對照!A:C,2,0),"") -> 錢亮均 | AF65: =IFERROR(VLOOKUP(J65&K65,對照!A:C,3,0),"") -> 台北營銷處
C66: TT00 | D66: 10 | E66: OM | F66: TW013788A1 | G66: 概念電器 | J66: TT229825 | K66: 錢 亮均 | L66: A | M66: Active | N66: 11007249 | O66: Dealer Sales_Taipei Team | P66: SAL | R66: SALES | S66: 46240 | T66: 401769 | U66: 11000151 | V66: LGETT | W66: false | X66: changsun.yang_chang sun Yang | Y66: 46203 | Z66: 0.80075231 | AA66: chiajung.wu_Chiajung Wu | AB66: 46240 | AC66: 0.61936343 | AE66: =IFERROR(VLOOKUP(J66&K66,對照!A:C,2,0),"") -> 錢亮均 | AF66: =IFERROR(VLOOKUP(J66&K66,對照!A:C,3,0),"") -> 台北營銷處
C67: TT00 | D67: 10 | E67: OM | F67: TW013793A1 | G67: 承泰電器 | J67: TT229825 | K67: 錢 亮均 | L67: A | M67: Active | N67: 11007249 | O67: Dealer Sales_Taipei Team | P67: SAL | R67: SALES | S67: 46240 | T67: 2958465 | U67: 11000151 | V67: LGETT | W67: false | X67: chiajung.wu_Chiajung Wu | Y67: 46240 | Z67: 0.58498843 | AA67: chiajung.wu_Chiajung Wu | AB67: 46240 | AC67: 0.58498843 | AE67: =IFERROR(VLOOKUP(J67&K67,對照!A:C,2,0),"") -> 錢亮均 | AF67: =IFERROR(VLOOKUP(J67&K67,對照!A:C,3,0),"") -> 台北營銷處
C68: TT00 | D68: 10 | E68: OM | F68: TW014410A1 | G68: 益大家電 | H68: TW014410 | I68: 益大家電事業有限公司 | J68: TT229825 | K68: 錢 亮均 | L68: A | M68: Active | N68: 11007249 | O68: Dealer Sales_Taipei Team | P68: SAL | R68: SALES | S68: 46240 | T68: 401769 | U68: 11000151 | V68: LGETT | W68: false | X68: changsun.yang_chang sun Yang | Y68: 46203 | Z68: 0.80075231 | AA68: chiajung.wu_Chiajung Wu | AB68: 46240 | AC68: 0.57984954 | AE68: =IFERROR(VLOOKUP(J68&K68,對照!A:C,2,0),"") -> 錢亮均 | AF68: =IFERROR(VLOOKUP(J68&K68,對照!A:C,3,0),"") -> 台北營銷處
C69: TT00 | D69: 10 | E69: OM | F69: TW016546A1 | G69: 富士多媒體 | H69: TWSG002933 | I69: 富士多媒體 | J69: TT229825 | K69: 錢 亮均 | L69: A | M69: Active | N69: 11007249 | O69: Dealer Sales_Taipei Team | P69: SAL | R69: SALES | S69: 46240 | T69: 401769 | U69: 11000151 | V69: LGETT | W69: false | X69: changsun.yang_chang sun Yang | Y69: 46203 | Z69: 0.80075231 | AA69: chiajung.wu_Chiajung Wu | AB69: 46240 | AC69: 0.66434028 | AE69: =IFERROR(VLOOKUP(J69&K69,對照!A:C,2,0),"") -> 錢亮均 | AF69: =IFERROR(VLOOKUP(J69&K69,對照!A:C,3,0),"") -> 台北營銷處
C70: TT00 | D70: 10 | E70: OM | F70: TW016697A1 | G70: 東昇電業行 | H70: TWSG000466 | I70: 東昇電業行 | J70: TT229825 | K70: 錢 亮均 | L70: A | M70: Active | N70: 11007249 | O70: Dealer Sales_Taipei Team | P70: SAL | R70: SALES | S70: 46240 | T70: 401769 | U70: 11000151 | V70: LGETT | W70: false | X70: changsun.yang_chang sun Yang | Y70: 46203 | Z70: 0.80075231 | AA70: chiajung.wu_Chiajung Wu | AB70: 46240 | AC70: 0.66583333 | AE70: =IFERROR(VLOOKUP(J70&K70,對照!A:C,2,0),"") -> 錢亮均 | AF70: =IFERROR(VLOOKUP(J70&K70,對照!A:C,3,0),"") -> 台北營銷處
C71: TT00 | D71: 10 | E71: OM | F71: TW017542A1 | G71: 嘉豐電器 | J71: TT229825 | K71: 錢 亮均 | L71: A | M71: Active | N71: 11007249 | O71: Dealer Sales_Taipei Team | P71: SAL | R71: SALES | S71: 46240 | T71: 401769 | U71: 11000151 | V71: LGETT | W71: false | X71: changsun.yang_chang sun Yang | Y71: 46203 | Z71: 0.80075231 | AA71: chiajung.wu_Chiajung Wu | AB71: 46240 | AC71: 0.66675926 | AE71: =IFERROR(VLOOKUP(J71&K71,對照!A:C,2,0),"") -> 錢亮均 | AF71: =IFERROR(VLOOKUP(J71&K71,對照!A:C,3,0),"") -> 台北營銷處
C72: TT00 | D72: 10 | E72: OM | F72: TW019079A1 | G72: 品毅空調 | J72: TT229825 | K72: 錢 亮均 | L72: A | M72: Active | N72: 11007249 | O72: Dealer Sales_Taipei Team | P72: SAL | R72: SALES | S72: 46240 | T72: 401769 | U72: 11000151 | V72: LGETT | W72: false | X72: changsun.yang_chang sun Yang | Y72: 46203 | Z72: 0.80075231 | AA72: chiajung.wu_Chiajung Wu | AB72: 46240 | AC72: 0.70376157 | AE72: =IFERROR(VLOOKUP(J72&K72,對照!A:C,2,0),"") -> 錢亮均 | AF72: =IFERROR(VLOOKUP(J72&K72,對照!A:C,3,0),"") -> 台北營銷處
C73: TT00 | D73: 10 | E73: OM | F73: TW019189A1 | G73: 怡沃拉國際有限公司 | J73: TT229825 | K73: 錢 亮均 | L73: A | M73: Active | N73: 11007249 | O73: Dealer Sales_Taipei Team | P73: SAL | R73: SALES | S73: 46240 | T73: 401769 | U73: 11000151 | V73: LGETT | W73: false | X73: changsun.yang_chang sun Yang | Y73: 46203 | Z73: 0.80075231 | AA73: chiajung.wu_Chiajung Wu | AB73: 46240 | AC73: 0.70456019 | AE73: =IFERROR(VLOOKUP(J73&K73,對照!A:C,2,0),"") -> 錢亮均 | AF73: =IFERROR(VLOOKUP(J73&K73,對照!A:C,3,0),"") -> 台北營銷處
C74: TT00 | D74: 10 | E74: OM | F74: TW019189A1 | G74: 怡沃拉國際有限公司 | H74: TWSG003647 | I74: 怡沃拉(汐止自助倉) | J74: TT229825 | K74: 錢 亮均 | L74: A | M74: Active | N74: 11007249 | O74: Dealer Sales_Taipei Team | P74: SAL | R74: SALES | S74: 46240 | T74: 401769 | U74: 11000151 | V74: LGETT | W74: false | X74: changsun.yang_chang sun Yang | Y74: 46203 | Z74: 0.80075231 | AA74: chiajung.wu_Chiajung Wu | AB74: 46240 | AC74: 0.70456019 | AE74: =IFERROR(VLOOKUP(J74&K74,對照!A:C,2,0),"") -> 錢亮均 | AF74: =IFERROR(VLOOKUP(J74&K74,對照!A:C,3,0),"") -> 台北營銷處
C75: TT00 | D75: 10 | E75: OM | F75: TW019189A1 | G75: 怡沃拉國際有限公司 | H75: TWSG003435 | I75: 怡沃拉國際有限公司 | J75: TT229825 | K75: 錢 亮均 | L75: A | M75: Active | N75: 11007249 | O75: Dealer Sales_Taipei Team | P75: SAL | R75: SALES | S75: 46240 | T75: 401769 | U75: 11000151 | V75: LGETT | W75: false | X75: changsun.yang_chang sun Yang | Y75: 46203 | Z75: 0.80075231 | AA75: chiajung.wu_Chiajung Wu | AB75: 46240 | AC75: 0.70456019 | AE75: =IFERROR(VLOOKUP(J75&K75,對照!A:C,2,0),"") -> 錢亮均 | AF75: =IFERROR(VLOOKUP(J75&K75,對照!A:C,3,0),"") -> 台北營銷處
C76: TT00 | D76: 10 | E76: OM | F76: TW019202A1 | G76: 達澄電器行 | J76: TT229825 | K76: 錢 亮均 | L76: A | M76: Active | N76: 11007249 | O76: Dealer Sales_Taipei Team | P76: SAL | R76: SALES | S76: 46240 | T76: 401769 | U76: 11000151 | V76: LGETT | W76: false | X76: changsun.yang_chang sun Yang | Y76: 46203 | Z76: 0.80075231 | AA76: chiajung.wu_Chiajung Wu | AB76: 46240 | AC76: 0.7065625 | AE76: =IFERROR(VLOOKUP(J76&K76,對照!A:C,2,0),"") -> 錢亮均 | AF76: =IFERROR(VLOOKUP(J76&K76,對照!A:C,3,0),"") -> 台北營銷處
C77: TT00 | D77: 10 | E77: OM | F77: TW019207A1 | G77: 華綺電器有限公司 | J77: TT229825 | K77: 錢 亮均 | L77: A | M77: Active | N77: 11007249 | O77: Dealer Sales_Taipei Team | P77: SAL | R77: SALES | S77: 46240 | T77: 401769 | U77: 11000151 | V77: LGETT | W77: false | X77: changsun.yang_chang sun Yang | Y77: 46203 | Z77: 0.80075231 | AA77: chiajung.wu_Chiajung Wu | AB77: 46240 | AC77: 0.70590278 | AE77: =IFERROR(VLOOKUP(J77&K77,對照!A:C,2,0),"") -> 錢亮均 | AF77: =IFERROR(VLOOKUP(J77&K77,對照!A:C,3,0),"") -> 台北營銷處
C78: TT00 | D78: 10 | E78: OM | F78: TW219182A1 | G78: 雅光 | H78: TW219182 | I78: 雅光 | J78: TT229825 | K78: 錢 亮均 | L78: A | M78: Active | N78: 11007249 | O78: Dealer Sales_Taipei Team | P78: SAL | R78: SALES | S78: 46240 | T78: 401769 | U78: 11000151 | V78: LGETT | W78: false | X78: changsun.yang_chang sun Yang | Y78: 46203 | Z78: 0.80075231 | AA78: chiajung.wu_Chiajung Wu | AB78: 46240 | AC78: 0.57591435 | AE78: =IFERROR(VLOOKUP(J78&K78,對照!A:C,2,0),"") -> 錢亮均 | AF78: =IFERROR(VLOOKUP(J78&K78,對照!A:C,3,0),"") -> 台北營銷處
C79: TT00 | D79: 10 | E79: OM | F79: TW219369A1 | G79: 銘卿整合工程有限公司 | J79: TT229825 | K79: 錢 亮均 | L79: A | M79: Active | N79: 11007249 | O79: Dealer Sales_Taipei Team | P79: SAL | R79: SALES | S79: 46240 | T79: 401769 | U79: 11000151 | V79: LGETT | W79: false | X79: changsun.yang_chang sun Yang | Y79: 46203 | Z79: 0.80075231 | AA79: chiajung.wu_Chiajung Wu | AB79: 46240 | AC79: 0.67017361 | AE79: =IFERROR(VLOOKUP(J79&K79,對照!A:C,2,0),"") -> 錢亮均 | AF79: =IFERROR(VLOOKUP(J79&K79,對照!A:C,3,0),"") -> 台北營銷處
C80: TT00 | D80: 10 | E80: OM | F80: TW219389A1 | G80: 鴻馨家電有限公司 | J80: TT229825 | K80: 錢 亮均 | L80: A | M80: Active | N80: 11007249 | O80: Dealer Sales_Taipei Team | P80: SAL | R80: SALES | S80: 46240 | T80: 401769 | U80: 11000151 | V80: LGETT | W80: false | X80: changsun.yang_chang sun Yang | Y80: 46203 | Z80: 0.80075231 | AA80: chiajung.wu_Chiajung Wu | AB80: 46240 | AC80: 0.67715278 | AE80: =IFERROR(VLOOKUP(J80&K80,對照!A:C,2,0),"") -> 錢亮均 | AF80: =IFERROR(VLOOKUP(J80&K80,對照!A:C,3,0),"") -> 台北營銷處
C81: TT00 | D81: 10 | E81: OM | F81: TW219461A1 | G81: 自在森林有限公司 | J81: TT229825 | K81: 錢 亮均 | L81: A | M81: Active | N81: 11007249 | O81: Dealer Sales_Taipei Team | P81: SAL | R81: SALES | S81: 46240 | T81: 401769 | U81: 11000151 | V81: LGETT | W81: false | X81: changsun.yang_chang sun Yang | Y81: 46203 | Z81: 0.80075231 | AA81: chiajung.wu_Chiajung Wu | AB81: 46240 | AC81: 0.67868056 | AE81: =IFERROR(VLOOKUP(J81&K81,對照!A:C,2,0),"") -> 錢亮均 | AF81: =IFERROR(VLOOKUP(J81&K81,對照!A:C,3,0),"") -> 台北營銷處
C82: TT00 | D82: 10 | E82: OM | F82: TW219513A1 | G82: 東馳企業有限公司 | J82: TT229825 | K82: 錢 亮均 | L82: A | M82: Active | N82: 11007249 | O82: Dealer Sales_Taipei Team | P82: SAL | R82: SALES | S82: 46240 | T82: 401769 | U82: 11000151 | V82: LGETT | W82: false | X82: changsun.yang_chang sun Yang | Y82: 46203 | Z82: 0.80075231 | AA82: chiajung.wu_Chiajung Wu | AB82: 46240 | AC82: 0.55587963 | AE82: =IFERROR(VLOOKUP(J82&K82,對照!A:C,2,0),"") -> 錢亮均 | AF82: =IFERROR(VLOOKUP(J82&K82,對照!A:C,3,0),"") -> 台北營銷處
C83: TT00 | D83: 10 | E83: OM | F83: TW219538A1 | G83: 日信空調行 | J83: TT229825 | K83: 錢 亮均 | L83: A | M83: Active | N83: 11007249 | O83: Dealer Sales_Taipei Team | P83: SAL | R83: SALES | S83: 46240 | T83: 401769 | U83: 11000151 | V83: LGETT | W83: false | X83: changsun.yang_chang sun Yang | Y83: 46203 | Z83: 0.80075231 | AA83: chiajung.wu_Chiajung Wu | AB83: 46240 | AC83: 0.70315972 | AE83: =IFERROR(VLOOKUP(J83&K83,對照!A:C,2,0),"") -> 錢亮均 | AF83: =IFERROR(VLOOKUP(J83&K83,對照!A:C,3,0),"") -> 台北營銷處
C84: TT00 | D84: 10 | E84: OM | F84: TW014622A1 | G84: 百裕 | J84: TT229825 | K84: 錢 亮均 | L84: A | M84: Active | N84: 11007249 | O84: Dealer Sales_Taipei Team | P84: SAL | R84: SALES | S84: 46239 | T84: 401769 | U84: 11000151 | V84: LGETT | W84: false | X84: changsun.yang_chang sun Yang | Y84: 46203 | Z84: 0.80075231 | AA84: chiajung.wu_Chiajung Wu | AB84: 46240 | AC84: 0.54770833 | AE84: =IFERROR(VLOOKUP(J84&K84,對照!A:C,2,0),"") -> 錢亮均 | AF84: =IFERROR(VLOOKUP(J84&K84,對照!A:C,3,0),"") -> 台北營銷處
C85: TT00 | D85: 10 | E85: OM | F85: TW016793A1 | G85: 小楊家電行 | H85: TWSG000256 | I85: 小楊(中和) | J85: TT229825 | K85: 錢 亮均 | L85: A | M85: Active | N85: 11007249 | O85: Dealer Sales_Taipei Team | P85: SAL | R85: SALES | S85: 46239 | T85: 2958465 | U85: 11000151 | V85: LGETT | W85: false | X85: chiajung.wu_Chiajung Wu | Y85: 46239 | Z85: 0.37466435 | AA85: chiajung.wu_Chiajung Wu | AB85: 46239 | AC85: 0.37466435 | AE85: =IFERROR(VLOOKUP(J85&K85,對照!A:C,2,0),"") -> 錢亮均 | AF85: =IFERROR(VLOOKUP(J85&K85,對照!A:C,3,0),"") -> 台北營銷處
C86: TT00 | D86: 10 | E86: OM | F86: TW016793A1 | G86: 小楊家電行 | H86: TWSG000258 | I86: 小楊(日月光) | J86: TT229825 | K86: 錢 亮均 | L86: A | M86: Active | N86: 11007249 | O86: Dealer Sales_Taipei Team | P86: SAL | R86: SALES | S86: 46239 | T86: 2958465 | U86: 11000151 | V86: LGETT | W86: false | X86: chiajung.wu_Chiajung Wu | Y86: 46239 | Z86: 0.37466435 | AA86: chiajung.wu_Chiajung Wu | AB86: 46239 | AC86: 0.37466435 | AE86: =IFERROR(VLOOKUP(J86&K86,對照!A:C,2,0),"") -> 錢亮均 | AF86: =IFERROR(VLOOKUP(J86&K86,對照!A:C,3,0),"") -> 台北營銷處
C87: TT00 | D87: 10 | E87: OM | F87: TW019203A1 | G87: 保發電器有限公司 | J87: TT229825 | K87: 錢 亮均 | L87: A | M87: Active | N87: 11007249 | O87: Dealer Sales_Taipei Team | P87: SAL | R87: SALES | S87: 46239 | T87: 401769 | U87: 11000151 | V87: LGETT | W87: false | X87: changsun.yang_chang sun Yang | Y87: 46203 | Z87: 0.80075231 | AA87: chiajung.wu_Chiajung Wu | AB87: 46240 | AC87: 0.55434028 | AE87: =IFERROR(VLOOKUP(J87&K87,對照!A:C,2,0),"") -> 錢亮均 | AF87: =IFERROR(VLOOKUP(J87&K87,對照!A:C,3,0),"") -> 台北營銷處
C88: TT00 | D88: 10 | E88: OM | F88: TW010429A1 | G88: 金亞實業 | J88: TT229825 | K88: 錢 亮均 | L88: A | M88: Active | N88: 11007249 | O88: Dealer Sales_Taipei Team | P88: SAL | R88: SALES | S88: 46238 | T88: 401769 | U88: 11000151 | V88: LGETT | W88: false | X88: changsun.yang_chang sun Yang | Y88: 46203 | Z88: 0.80075231 | AA88: selena.sun_Chuni Sun | AB88: 46238 | AC88: 0.47413194 | AE88: =IFERROR(VLOOKUP(J88&K88,對照!A:C,2,0),"") -> 錢亮均 | AF88: =IFERROR(VLOOKUP(J88&K88,對照!A:C,3,0),"") -> 台北營銷處
C89: TT00 | D89: 10 | E89: OM | F89: TW010429A1 | G89: 金亞實業 | H89: TWSG002852 | I89: 金亞(映像) | J89: TT229825 | K89: 錢 亮均 | L89: A | M89: Active | N89: 11007249 | O89: Dealer Sales_Taipei Team | P89: SAL | R89: SALES | S89: 46238 | T89: 401769 | U89: 11000151 | V89: LGETT | W89: false | X89: changsun.yang_chang sun Yang | Y89: 46203 | Z89: 0.80075231 | AA89: selena.sun_Chuni Sun | AB89: 46238 | AC89: 0.47413194 | AE89: =IFERROR(VLOOKUP(J89&K89,對照!A:C,2,0),"") -> 錢亮均 | AF89: =IFERROR(VLOOKUP(J89&K89,對照!A:C,3,0),"") -> 台北營銷處
C90: TT00 | D90: 10 | E90: OM | F90: TW010429A1 | G90: 金亞實業 | H90: TWSG002956 | I90: 金亞實業有限公司(倉庫) | J90: TT229825 | K90: 錢 亮均 | L90: A | M90: Active | N90: 11007249 | O90: Dealer Sales_Taipei Team | P90: SAL | R90: SALES | S90: 46238 | T90: 401769 | U90: 11000151 | V90: LGETT | W90: false | X90: changsun.yang_chang sun Yang | Y90: 46203 | Z90: 0.80075231 | AA90: selena.sun_Chuni Sun | AB90: 46238 | AC90: 0.47413194 | AE90: =IFERROR(VLOOKUP(J90&K90,對照!A:C,2,0),"") -> 錢亮均 | AF90: =IFERROR(VLOOKUP(J90&K90,對照!A:C,3,0),"") -> 台北營銷處
C91: TT00 | D91: 10 | E91: OM | F91: TW010429A1 | G91: 金亞實業 | H91: TW010429 | I91: 金亞實業有限公司 | J91: TT229825 | K91: 錢 亮均 | L91: A | M91: Active | N91: 11007249 | O91: Dealer Sales_Taipei Team | P91: SAL | R91: SALES | S91: 46238 | T91: 401769 | U91: 11000151 | V91: LGETT | W91: false | X91: changsun.yang_chang sun Yang | Y91: 46203 | Z91: 0.80075231 | AA91: selena.sun_Chuni Sun | AB91: 46238 | AC91: 0.47413194 | AE91: =IFERROR(VLOOKUP(J91&K91,對照!A:C,2,0),"") -> 錢亮均 | AF91: =IFERROR(VLOOKUP(J91&K91,對照!A:C,3,0),"") -> 台北營銷處
C92: TT00 | D92: 10 | E92: OM | F92: TW010431A1 | G92: 萬豐視聽 | J92: TT229825 | K92: 錢 亮均 | L92: A | M92: Active | N92: 11007249 | O92: Dealer Sales_Taipei Team | P92: SAL | R92: SALES | S92: 46238 | T92: 401769 | U92: 11000151 | V92: LGETT | W92: false | X92: changsun.yang_chang sun Yang | Y92: 46203 | Z92: 0.80075231 | AA92: chiajung.wu_Chiajung Wu | AB92: 46238 | AC92: 0.86554398 | AE92: =IFERROR(VLOOKUP(J92&K92,對照!A:C,2,0),"") -> 錢亮均 | AF92: =IFERROR(VLOOKUP(J92&K92,對照!A:C,3,0),"") -> 台北營銷處
C93: TT00 | D93: 10 | E93: OM | F93: TW010431A1 | G93: 萬豐視聽 | H93: TW010431 | I93: 萬豐視聽電業有限公司 | J93: TT229825 | K93: 錢 亮均 | L93: A | M93: Active | N93: 11007249 | O93: Dealer Sales_Taipei Team | P93: SAL | R93: SALES | S93: 46238 | T93: 401769 | U93: 11000151 | V93: LGETT | W93: false | X93: changsun.yang_chang sun Yang | Y93: 46203 | Z93: 0.80075231 | AA93: chiajung.wu_Chiajung Wu | AB93: 46238 | AC93: 0.86554398 | AE93: =IFERROR(VLOOKUP(J93&K93,對照!A:C,2,0),"") -> 錢亮均 | AF93: =IFERROR(VLOOKUP(J93&K93,對照!A:C,3,0),"") -> 台北營銷處
C94: TT00 | D94: 10 | E94: OM | F94: TW010431A1 | G94: 萬豐視聽 | H94: TWSG002707 | I94: 萬豐(佳士達) | J94: TT229825 | K94: 錢 亮均 | L94: A | M94: Active | N94: 11007249 | O94: Dealer Sales_Taipei Team | P94: SAL | R94: SALES | S94: 46238 | T94: 401769 | U94: 11000151 | V94: LGETT | W94: false | X94: changsun.yang_chang sun Yang | Y94: 46203 | Z94: 0.80075231 | AA94: chiajung.wu_Chiajung Wu | AB94: 46238 | AC94: 0.86554398 | AE94: =IFERROR(VLOOKUP(J94&K94,對照!A:C,2,0),"") -> 錢亮均 | AF94: =IFERROR(VLOOKUP(J94&K94,對照!A:C,3,0),"") -> 台北營銷處
C95: TT00 | D95: 10 | E95: OM | F95: TW010688A1 | G95: 協良電器有限公司 | H95: TWSG003490 | I95: 協良(門市) | J95: TT229825 | K95: 錢 亮均 | L95: A | M95: Active | N95: 11007249 | O95: Dealer Sales_Taipei Team | P95: SAL | R95: SALES | S95: 46238 | T95: 401769 | U95: 11000151 | V95: LGETT | W95: false | X95: changsun.yang_chang sun Yang | Y95: 46203 | Z95: 0.80075231 | AA95: chiajung.wu_Chiajung Wu | AB95: 46239 | AC95: 0.35849537 | AE95: =IFERROR(VLOOKUP(J95&K95,對照!A:C,2,0),"") -> 錢亮均 | AF95: =IFERROR(VLOOKUP(J95&K95,對照!A:C,3,0),"") -> 台北營銷處
C96: TT00 | D96: 10 | E96: OM | F96: TW010688A1 | G96: 協良電器有限公司 | J96: TT229825 | K96: 錢 亮均 | L96: A | M96: Active | N96: 11007249 | O96: Dealer Sales_Taipei Team | P96: SAL | R96: SALES | S96: 46238 | T96: 401769 | U96: 11000151 | V96: LGETT | W96: false | X96: changsun.yang_chang sun Yang | Y96: 46203 | Z96: 0.80075231 | AA96: chiajung.wu_Chiajung Wu | AB96: 46239 | AC96: 0.35849537 | AE96: =IFERROR(VLOOKUP(J96&K96,對照!A:C,2,0),"") -> 錢亮均 | AF96: =IFERROR(VLOOKUP(J96&K96,對照!A:C,3,0),"") -> 台北營銷處
C97: TT00 | D97: 10 | E97: OM | F97: TW010688A1 | G97: 協良電器有限公司 | H97: TWSG003473 | I97: 協良電器有限公司 | J97: TT229825 | K97: 錢 亮均 | L97: A | M97: Active | N97: 11007249 | O97: Dealer Sales_Taipei Team | P97: SAL | R97: SALES | S97: 46238 | T97: 401769 | U97: 11000151 | V97: LGETT | W97: false | X97: changsun.yang_chang sun Yang | Y97: 46203 | Z97: 0.80075231 | AA97: chiajung.wu_Chiajung Wu | AB97: 46239 | AC97: 0.35849537 | AE97: =IFERROR(VLOOKUP(J97&K97,對照!A:C,2,0),"") -> 錢亮均 | AF97: =IFERROR(VLOOKUP(J97&K97,對照!A:C,3,0),"") -> 台北營銷處
C98: TT00 | D98: 10 | E98: OM | F98: TW010808A1 | G98: 品銓電器有限公司 | H98: TWSG001895 | I98: 品銓電器有限公司 | J98: TT229825 | K98: 錢 亮均 | L98: A | M98: Active | N98: 11007249 | O98: Dealer Sales_Taipei Team | P98: SAL | R98: SALES | S98: 46238 | T98: 401769 | U98: 11000151 | V98: LGETT | W98: false | X98: changsun.yang_chang sun Yang | Y98: 46203 | Z98: 0.80075231 | AA98: chiajung.wu_Chiajung Wu | AB98: 46239 | AC98: 0.35777778 | AE98: =IFERROR(VLOOKUP(J98&K98,對照!A:C,2,0),"") -> 錢亮均 | AF98: =IFERROR(VLOOKUP(J98&K98,對照!A:C,3,0),"") -> 台北營銷處
C99: TT00 | D99: 10 | E99: OM | F99: TW010817A1 | G99: 郁翔電器 | H99: TW010817 | I99: 郁翔電器有限公司 | J99: TT229825 | K99: 錢 亮均 | L99: A | M99: Active | N99: 11007249 | O99: Dealer Sales_Taipei Team | P99: SAL | R99: SALES | S99: 46238 | T99: 401769 | U99: 11000151 | V99: LGETT | W99: false | X99: changsun.yang_chang sun Yang | Y99: 46203 | Z99: 0.80075231 | AA99: chiajung.wu_Chiajung Wu | AB99: 46239 | AC99: 0.64590278 | AE99: =IFERROR(VLOOKUP(J99&K99,對照!A:C,2,0),"") -> 錢亮均 | AF99: =IFERROR(VLOOKUP(J99&K99,對照!A:C,3,0),"") -> 台北營銷處
C100: TT00 | D100: 10 | E100: OM | F100: TW010841A1 | G100: 佳禾 | H100: TWSG001973 | I100: 佳禾貿易(送貨住址) | J100: TT229825 | K100: 錢 亮均 | L100: A | M100: Active | N100: 11007249 | O100: Dealer Sales_Taipei Team | P100: SAL | R100: SALES | S100: 46238 | T100: 401769 | U100: 11000151 | V100: LGETT | W100: false | X100: chiajung.wu_Chiajung Wu | Y100: 46238 | Z100: 0.92165509 | AA100: chiajung.wu_Chiajung Wu | AB100: 46238 | AC100: 0.92165509 | AE100: =IFERROR(VLOOKUP(J100&K100,對照!A:C,2,0),"") -> 錢亮均 | AF100: =IFERROR(VLOOKUP(J100&K100,對照!A:C,3,0),"") -> 台北營銷處
...

Sheet 對照
A1: Salesperson Name | B1: 業務員 | C1: 業務員單位 | L1: Sold to | M1: Legal Entity | N1: Sold Name | O1: 合併Sold to | P1: 合併Legal Entity | Q1: 合併Sold Name | R1: 特殊 | X1: 批店-Sold to | Y1: 批店-Sold Name | Z1: 特殊
A2: TT230713姜 泊昆 | B2: 姜泊昆 | C2: IT Part | L2: TW016267A1 | M2: TW01626700 | N2: 立誠電器有限公司 | O2: TW010823A1 | P2: TW01082300 | Q2: 鎮吉實業有限公司 | X2: TW010117A1 | Y2: 金長益電器 | Z2: 批店
A3: TT229829施 漢鵬 | B3: 施漢鵬 | C3: MMCS | L3: TW011309A1 | M3: TW01130900 | N3: 廣昌電器行 | O3: TW011309A1 | P3: TW01130900 | Q3: 廣昌電器行 | X3: TW010118A1 | Y3: 格愛陞 | Z3: 批店
A4: TT230775褚 家鳴 | B4: 褚家鳴 | C4: 桃竹營銷處 | L4: TW219353A1 | M4: TW21935300 | N4: 廣宜電器行 | O4: TW011309A1 | P4: TW01130900 | Q4: 廣昌電器行 | X4: TW010455A1 | Y4: 昇廣電器 | Z4: 批店
A5: TT001185陳 勇志 | B5: 陳勇志 | C5: MMCS | L5: TW016815A1 | M5: TW01681500 | N5: 萊旺電器行 | O5: TW012526A1 | P5: TW01252600 | Q5: 萊旺企業有限公司 | X5: TW010662A1 | Y5: 老雙億實業 | Z5: 批店
A6: TT230774粘 棋欽 | B6: 粘棋欽 | C6: 嘉南營銷處 | L6: TW013498A1 | M6: TW01349800 | N6: 同勝電器有限公司 | O6: TW013498A1 | P6: TW01349800 | Q6: 同勝電器有限公司 | X6: TW010706A1 | Y6: 統偉視聽工程有限公司 | Z6: AV店
A7: TT001436陳 俊宏 | B7: 陳俊宏(Rental) | C7: Rental | L7: TW219209A1 | M7: TW21920900 | N7: 統勝電器有限公司 | O7: TW013498A1 | P7: TW01349800 | Q7: 同勝電器有限公司 | X7: TW010823A1 | Y7: 鎮吉實業 | Z7: 批店
A8: TT001496歐 俊賢 | B8: 歐俊賢 | C8: 嘉南營銷處 | L8: TW219562A1 | M8: TW21956200 | N8: 甲組電器有限公司 | O8: TW013498A1 | P8: TW01349800 | Q8: 同勝電器有限公司 | X8: TW010830A1 | Y8: 承德國際有限公司 | Z8: AV店
A9: TT001305黃 坤鎮 | B9: 黃坤鎮 | C9: 嘉南營銷處 | L9: TW009961A1 | M9: TW00996100 | N9: 慧聲電器行 | O9: TW016117A1 | P9: TW01611700 | Q9: 慧榮電器有限公司 | X9: TW010841A1 | Y9: 佳禾 | Z9: 批店
A10: TT229769陳 慶全 | B10: 陳慶全 | C10: 台中營銷處 | L10: TW016117A1 | M10: TW01611700 | N10: 慧榮電器有限公司 | O10: TW016117A1 | P10: TW01611700 | Q10: 慧榮電器有限公司 | X10: TW010844A1 | Y10: 得興電器 | Z10: 批店
A11: TT230594江 柏慶 | B11: 江柏慶 | C11: 嘉南營銷處 | L11: TW219227A1 | M11: TW21922700 | N11: 鼎極家電有限公司 | O11: TW017534A1 | P11: TW01753400 | Q11: 國際極品科技有限公司 | X11: TW012439A1 | Y11: 悅鼎電器有限公司 | Z11: AV店
A12: TT001081陳 志豐 | B12: 陳志豐 | C12: 高屏營銷處 | L12: TW017534A1 | M12: TW01753400 | N12: 國際極品科技有限公司 | O12: TW017534A1 | P12: TW01753400 | Q12: 國際極品科技有限公司 | X12: TW012757A1 | Y12: 華笙音響企業有限公司 | Z12: AV店
A13: TT230543鄭 伊善 | B13: 鄭伊善 | C13: AC Team | L13: TW012602A1 | M13: TW01260200 | N13: 姿芳企業有限公司 | O13: TW018135A1 | P13: TW01813500 | Q13: 姿芳科技有限公司 | X13: TW012762A1 | Y13: 大銀幕視聽音響有限公司 | Z13: AV店
... A38: TT230494郭 本威 | B38: 郭本威 | C38: OBS | L38: TW219232A1 | M38: TW21923200 | N38: 宸逸企業社 | O38: TW219252A1 | P38: TW21925200 | Q38: 黃金林企業有限公司 | X38: TW219289A1 | Y38: 鈺陞有限公司 | Z38: 批店
A39: TT230648吳 睿涵 | B39: 吳睿涵 | C39: E-Commerce | L39: TW219252A1 | M39: TW21925200 | N39: 黃金林企業有限公司 | O39: TW219252A1 | P39: TW21925200 | Q39: 黃金林企業有限公司
A40: TT230411林 宜慧 | B40: 林宜慧 | C40: E-Commerce | L40: TW012796A1 | M40: TW01279600 | N40: 泰梭股份有限公司 | O40: TW219256A1 | P40: TW21925600 | Q40: 泰梭企業社
A41: TT230642吳 沛綺 | B41: 吳沛綺 | C41: SCM | L41: TW219256A1 | M41: TW21925600 | N41: 泰梭企業社 | O41: TW219256A1 | P41: TW21925600 | Q41: 泰梭企業社
A42: TT230686胡 智偉 | B42: 胡智偉 | C42: 台中營銷處 | L42: TW014840A1 | M42: TW01484000 | N42: 益昇商行 | O42: TW219258A1 | P42: TW21925800 | Q42: 倉泉有限公司
A43: TT230790莊 淳然 | B43: 莊淳然 | C43: ID Part | L43: TW219258A1 | M43: TW21925800 | N43: 倉泉有限公司 | O43: TW219258A1 | P43: TW21925800 | Q43: 倉泉有限公司
A44: TT001518羅 時景 | B44: 羅時景 | C44: ETC | L44: TW219259A1 | M44: TW21925900 | N44: 尚合雅有限公司 | O44: TW219259A1 | P44: TW21925900 | Q44: 尚合雅有限公司
A45: TT230808廖 婉婷 | B45: 廖婉婷 | C45: B2B2C | L45: TW219473A1 | M45: TW21947300 | N45: 金合雅有限公司 | O45: TW219259A1 | P45: TW21925900 | Q45: 尚合雅有限公司
A46: TT230838陳 良緒 | B46: 陳良緒 | C46: Admin | L46: TW219284A1 | M46: TW21928400 | N46: 佳美百事購有限公司 | O46: TW219284A1 | P46: TW21928400 | Q46: 佳美百事購有限公司
A47: TT230878陳 士騏 | B47: 陳士騏 | C47: E-Commerce | L47: TW219189A1 | M47: TW21918900 | N47: 佳美電器行 | O47: TW219284A1 | P47: TW21928400 | Q47: 佳美百事購有限公司
A48: TT001406陳 俊宏 | B48: 陳俊宏 | C48: 百貨 | L48: TW219314A1 | M48: TW21931400 | N48: 翰鉅有限公司 | O48: TW219285A1 | P48: TW21928500 | Q48: 豪順興業有限公司
A49: TT230545吳 章瑋 | B49: 吳章瑋 | C49: AC Team | L49: TW219285A1 | M49: TW21928500 | N49: 豪順興業有限公司 | O49: TW219285A1 | P49: TW21928500 | Q49: 豪順興業有限公司
L50: TW009380A1 | M50: TW00938000 | N50: 世英電業行 | O50: TW219287A1 | P50: TW21928700 | Q50: 佳新電業有限公司
L51: TW219287A1 | M51: TW21928700 | N51: 佳新電業有限公司 | O51: TW219287A1 | P51: TW21928700 | Q51: 佳新電業有限公司
L52: TW219289A1 | M52: TW21928900 | N52: 鈺陞有限公司 | O52: TW219289A1 | P52: TW21928900 | Q52: 鈺陞有限公司
L53: TW010118A1 | M53: TW01011800 | N53: 格愛陞有限公司 | O53: TW219289A1 | P53: TW21928900 | Q53: 鈺陞有限公司
L54: TW219305A1 | M54: TW21930500 | N54: 銘鎧電器行 | O54: TW219305A1 | P54: TW21930500 | Q54: 銘鎧電器行
L55: TW010950A1 | M55: TW01095000 | N55: 強尼電器百貨大批發 | O55: TW219320A1 | P55: TW21932000 | Q55: 強尼電器行
L56: TW219320A1 | M56: TW21932000 | N56: 強尼電器行 | O56: TW219320A1 | P56: TW21932000 | Q56: 強尼電器行
L57: TW219326A1 | M57: TW21932600 | N57: 上加實業有限公司 | O57: TW219326A1 | P57: TW21932600 | Q57: 上加實業有限公司
L58: TW013768A1 | M58: TW01376800 | N58: 上加電器有限公司 | O58: TW219326A1 | P58: TW21932600 | Q58: 上加實業有限公司
L59: TW014724A1 | M59: TW01472400 | N59: 九瑜電氣行 | O59: TW219336A1 | P59: TW21933600 | Q59: 立宏空調科技有限公司
L60: TW219336A1 | M60: TW21933600 | N60: 立宏空調科技有限公司 | O60: TW219336A1 | P60: TW21933600 | Q60: 立宏空調科技有限公司
L61: TW014621A1 | M61: TW01462100 | N61: 南霸天電器有限公司 | O61: TW219617A1 | P61: TW21945500 | Q61: 九三電器有限公司
... L68: TW017154A1 | M68: TW01715400 | N68: 特家麗企業有限公司鹿港分公司 | O68: TW219581A1 | P68: TW21958100 | Q68: 特家麗家電生活館有限公司
